{"updated_at":"2026-04-23T11:40:44.217487+00:00","btc_price":77535.13,"btc_change_24h":-0.85,"current_signal":"neutral","last_signal_date":"2026-04-13","runs":20756,"account_a":{"name":"M1 (40\u20ac)","initial":40.0,"equity":39.4978,"cash":39.4978,"total_pnl":-0.3693,"total_pnl_pct":-1.26,"num_trades":23,"win_rate":39.1,"position":null,"trades":[{"side":"SHORT","entry_px":71014.59,"exit_px":70800.01,"exit_reason":"TIME_EXIT","pnl_net":0.0227,"pnl_pct":0.61,"leverage":3.0,"open_date":"2026-04-09T00:07:27.280958+00:00","close_date":"2026-04-09T00:37:29.797812+00:00"},{"side":"SHORT","entry_px":71310.14,"exit_px":72270.21,"exit_reason":"TIME_EXIT","pnl_net":-0.1689,"pnl_pct":-4.34,"leverage":3.0,"open_date":"2026-04-09T15:34:30.289830+00:00","close_date":"2026-04-09T16:04:38.081910+00:00"},{"side":"SHORT","entry_px":72238.7,"exit_px":71928.37,"exit_reason":"TIME_EXIT","pnl_net":0.0379,"pnl_pct":0.99,"leverage":3.0,"open_date":"2026-04-09T16:10:45.762905+00:00","close_date":"2026-04-09T16:40:35.619888+00:00"},{"side":"SHORT","entry_px":72132.38,"exit_px":72293.11,"exit_reason":"TIME_EXIT","pnl_net":-0.0369,"pnl_pct":-0.97,"leverage":3.0,"open_date":"2026-04-09T17:34:32.440495+00:00","close_date":"2026-04-09T18:04:29.684322+00:00"},{"side":"SHORT","entry_px":72178.16,"exit_px":71877.1,"exit_reason":"TIME_EXIT","pnl_net":0.0362,"pnl_pct":0.95,"leverage":3.0,"open_date":"2026-04-09T18:05:33.340811+00:00","close_date":"2026-04-09T18:35:34.470407+00:00"},{"side":"SHORT","entry_px":72198.57,"exit_px":72316.68,"exit_reason":"TIME_EXIT","pnl_net":-0.0301,"pnl_pct":-0.79,"leverage":3.0,"open_date":"2026-04-09T19:55:32.337788+00:00","close_date":"2026-04-09T20:25:29.183202+00:00"},{"side":"SHORT","entry_px":72236.1,"exit_px":72278.18,"exit_reason":"TIME_EXIT","pnl_net":-0.018,"pnl_pct":-0.47,"leverage":3.0,"open_date":"2026-04-09T21:14:31.647775+00:00","close_date":"2026-04-09T21:44:32.950707+00:00"},{"side":"SHORT","entry_px":71815.44,"exit_px":71951.05,"exit_reason":"TIME_EXIT","pnl_net":-0.0342,"pnl_pct":-0.87,"leverage":3.0,"open_date":"2026-04-10T00:07:27.498736+00:00","close_date":"2026-04-10T00:37:28.193865+00:00"},{"side":"SHORT","entry_px":72227.07,"exit_px":72218.7,"exit_reason":"TIME_EXIT","pnl_net":-0.0103,"pnl_pct":-0.27,"leverage":3.0,"open_date":"2026-04-10T01:57:29.972077+00:00","close_date":"2026-04-10T02:27:25.772993+00:00"},{"side":"SHORT","entry_px":72235.52,"exit_px":72124.48,"exit_reason":"TIME_EXIT","pnl_net":0.0063,"pnl_pct":0.16,"leverage":3.0,"open_date":"2026-04-10T05:33:27.378141+00:00","close_date":"2026-04-10T06:03:27.036407+00:00"},{"side":"SHORT","entry_px":71648.45,"exit_px":71733.83,"exit_reason":"TIME_EXIT","pnl_net":-0.0265,"pnl_pct":-0.66,"leverage":3.0,"open_date":"2026-04-10T08:15:40.778984+00:00","close_date":"2026-04-10T08:45:38.484577+00:00"},{"side":"SHORT","entry_px":71699.73,"exit_px":71754.37,"exit_reason":"TIME_EXIT","pnl_net":-0.0213,"pnl_pct":-0.53,"leverage":3.0,"open_date":"2026-04-10T09:20:37.029930+00:00","close_date":"2026-04-10T09:50:34.257031+00:00"},{"side":"LONG","entry_px":72720.95,"exit_px":72801.09,"exit_reason":"TIME_EXIT","pnl_net":0.0012,"pnl_pct":0.03,"leverage":3.0,"open_date":"2026-04-11T06:31:26.078999+00:00","close_date":"2026-04-11T07:01:32.001463+00:00"},{"side":"LONG","entry_px":71750.2,"exit_px":71675.3,"exit_reason":"TIME_EXIT","pnl_net":-0.0235,"pnl_pct":-0.61,"leverage":3.0,"open_date":"2026-04-12T06:18:31.647450+00:00","close_date":"2026-04-12T06:48:33.656037+00:00"},{"side":"SHORT","entry_px":70817.98,"exit_px":70782.69,"exit_reason":"TIME_EXIT","pnl_net":-0.0057,"pnl_pct":-0.15,"leverage":3.0,"open_date":"2026-04-12T14:49:31.581180+00:00","close_date":"2026-04-12T15:19:31.557594+00:00"},{"side":"SHORT","entry_px":70782.69,"exit_px":70912.73,"exit_reason":"TIME_EXIT","pnl_net":-0.0324,"pnl_pct":-0.85,"leverage":3.0,"open_date":"2026-04-12T15:19:31.557694+00:00","close_date":"2026-04-12T15:49:29.823540+00:00"},{"side":"SHORT","entry_px":70805.59,"exit_px":70690.41,"exit_reason":"TIME_EXIT","pnl_net":0.0071,"pnl_pct":0.19,"leverage":3.0,"open_date":"2026-04-12T22:06:33.958533+00:00","close_date":"2026-04-12T22:36:29.596287+00:00"},{"side":"SHORT","entry_px":70820.73,"exit_px":70749.51,"exit_reason":"TIME_EXIT","pnl_net":0.0001,"pnl_pct":0.0,"leverage":3.0,"open_date":"2026-04-12T22:40:35.941449+00:00","close_date":"2026-04-12T23:10:43.110297+00:00"},{"side":"SHORT","entry_px":70681.25,"exit_px":71063.91,"exit_reason":"TIME_EXIT","pnl_net":-0.0729,"pnl_pct":-1.92,"leverage":3.0,"open_date":"2026-04-13T00:08:28.139824+00:00","close_date":"2026-04-13T00:38:32.440151+00:00"},{"side":"SHORT","entry_px":70806.27,"exit_px":70713.49,"exit_reason":"TIME_EXIT","pnl_net":0.0035,"pnl_pct":0.09,"leverage":3.0,"open_date":"2026-04-13T05:13:30.616682+00:00","close_date":"2026-04-13T05:43:32.136431+00:00"},{"side":"SHORT","entry_px":70816.14,"exit_px":71010.73,"exit_reason":"TIME_EXIT","pnl_net":-0.0426,"pnl_pct":-1.12,"leverage":3.0,"open_date":"2026-04-13T05:51:32.986866+00:00","close_date":"2026-04-13T06:21:28.800920+00:00"},{"side":"LONG","entry_px":72535.93,"exit_px":72156.26,"exit_reason":"TIME_EXIT","pnl_net":-0.0729,"pnl_pct":-1.87,"leverage":3.0,"open_date":"2026-04-13T17:34:38.784833+00:00","close_date":"2026-04-13T18:05:41.243229+00:00"},{"side":"LONG","entry_px":72510.19,"exit_px":73279.18,"exit_reason":"TIME_EXIT","pnl_net":0.1119,"pnl_pct":2.88,"leverage":3.0,"open_date":"2026-04-13T19:22:31.694920+00:00","close_date":"2026-04-13T19:52:33.690112+00:00"}],"equity_history":[{"ts":"2026-04-23T08:18:36.159950+00:00","equity":39.4978},{"ts":"2026-04-23T08:19:34.818394+00:00","equity":39.4978},{"ts":"2026-04-23T08:20:47.911263+00:00","equity":39.4978},{"ts":"2026-04-23T08:21:33.267845+00:00","equity":39.4978},{"ts":"2026-04-23T08:22:41.067581+00:00","equity":39.4978},{"ts":"2026-04-23T08:23:36.710428+00:00","equity":39.4978},{"ts":"2026-04-23T08:24:44.453566+00:00","equity":39.4978},{"ts":"2026-04-23T08:25:36.429319+00:00","equity":39.4978},{"ts":"2026-04-23T08:26:35.315129+00:00","equity":39.4978},{"ts":"2026-04-23T08:27:35.362306+00:00","equity":39.4978},{"ts":"2026-04-23T08:28:36.659166+00:00","equity":39.4978},{"ts":"2026-04-23T08:29:37.341214+00:00","equity":39.4978},{"ts":"2026-04-23T08:30:58.669728+00:00","equity":39.4978},{"ts":"2026-04-23T08:31:38.704112+00:00","equity":39.4978},{"ts":"2026-04-23T08:32:38.554700+00:00","equity":39.4978},{"ts":"2026-04-23T08:33:41.361217+00:00","equity":39.4978},{"ts":"2026-04-23T08:34:35.155639+00:00","equity":39.4978},{"ts":"2026-04-23T08:35:42.235925+00:00","equity":39.4978},{"ts":"2026-04-23T08:36:40.268987+00:00","equity":39.4978},{"ts":"2026-04-23T08:37:39.556998+00:00","equity":39.4978},{"ts":"2026-04-23T08:38:38.499662+00:00","equity":39.4978},{"ts":"2026-04-23T08:39:39.892559+00:00","equity":39.4978},{"ts":"2026-04-23T08:40:46.356682+00:00","equity":39.4978},{"ts":"2026-04-23T08:41:35.112618+00:00","equity":39.4978},{"ts":"2026-04-23T08:42:40.832877+00:00","equity":39.4978},{"ts":"2026-04-23T08:43:36.044492+00:00","equity":39.4978},{"ts":"2026-04-23T08:44:39.053119+00:00","equity":39.4978},{"ts":"2026-04-23T08:45:47.935901+00:00","equity":39.4978},{"ts":"2026-04-23T08:46:41.999613+00:00","equity":39.4978},{"ts":"2026-04-23T08:47:38.524458+00:00","equity":39.4978},{"ts":"2026-04-23T08:48:39.262734+00:00","equity":39.4978},{"ts":"2026-04-23T08:49:39.172384+00:00","equity":39.4978},{"ts":"2026-04-23T08:50:43.734614+00:00","equity":39.4978},{"ts":"2026-04-23T08:51:40.543143+00:00","equity":39.4978},{"ts":"2026-04-23T08:52:41.869813+00:00","equity":39.4978},{"ts":"2026-04-23T08:53:36.761485+00:00","equity":39.4978},{"ts":"2026-04-23T08:54:38.723592+00:00","equity":39.4978},{"ts":"2026-04-23T08:55:39.101712+00:00","equity":39.4978},{"ts":"2026-04-23T08:56:39.552525+00:00","equity":39.4978},{"ts":"2026-04-23T08:57:36.664994+00:00","equity":39.4978},{"ts":"2026-04-23T08:58:38.055646+00:00","equity":39.4978},{"ts":"2026-04-23T08:59:36.848789+00:00","equity":39.4978},{"ts":"2026-04-23T09:01:11.296295+00:00","equity":39.4978},{"ts":"2026-04-23T09:02:40.353308+00:00","equity":39.4978},{"ts":"2026-04-23T09:03:40.288897+00:00","equity":39.4978},{"ts":"2026-04-23T09:04:37.016894+00:00","equity":39.4978},{"ts":"2026-04-23T09:05:43.736435+00:00","equity":39.4978},{"ts":"2026-04-23T09:06:39.611787+00:00","equity":39.4978},{"ts":"2026-04-23T09:07:36.238155+00:00","equity":39.4978},{"ts":"2026-04-23T09:08:30.381103+00:00","equity":39.4978},{"ts":"2026-04-23T09:09:37.380964+00:00","equity":39.4978},{"ts":"2026-04-23T09:10:43.435435+00:00","equity":39.4978},{"ts":"2026-04-23T09:11:36.705023+00:00","equity":39.4978},{"ts":"2026-04-23T09:12:45.609312+00:00","equity":39.4978},{"ts":"2026-04-23T09:13:41.958615+00:00","equity":39.4978},{"ts":"2026-04-23T09:14:36.150316+00:00","equity":39.4978},{"ts":"2026-04-23T09:15:47.567918+00:00","equity":39.4978},{"ts":"2026-04-23T09:16:36.190646+00:00","equity":39.4978},{"ts":"2026-04-23T09:17:36.677962+00:00","equity":39.4978},{"ts":"2026-04-23T09:18:39.754354+00:00","equity":39.4978},{"ts":"2026-04-23T09:19:34.436077+00:00","equity":39.4978},{"ts":"2026-04-23T09:20:47.183256+00:00","equity":39.4978},{"ts":"2026-04-23T09:21:35.910211+00:00","equity":39.4978},{"ts":"2026-04-23T09:22:35.719010+00:00","equity":39.4978},{"ts":"2026-04-23T09:23:34.029357+00:00","equity":39.4978},{"ts":"2026-04-23T09:24:39.986800+00:00","equity":39.4978},{"ts":"2026-04-23T09:25:41.879208+00:00","equity":39.4978},{"ts":"2026-04-23T09:26:37.860460+00:00","equity":39.4978},{"ts":"2026-04-23T09:27:39.861913+00:00","equity":39.4978},{"ts":"2026-04-23T09:28:39.013481+00:00","equity":39.4978},{"ts":"2026-04-23T09:29:43.083344+00:00","equity":39.4978},{"ts":"2026-04-23T09:30:59.781554+00:00","equity":39.4978},{"ts":"2026-04-23T09:31:34.258939+00:00","equity":39.4978},{"ts":"2026-04-23T09:32:40.091812+00:00","equity":39.4978},{"ts":"2026-04-23T09:33:39.249483+00:00","equity":39.4978},{"ts":"2026-04-23T09:34:37.936372+00:00","equity":39.4978},{"ts":"2026-04-23T09:35:43.593955+00:00","equity":39.4978},{"ts":"2026-04-23T09:36:39.378712+00:00","equity":39.4978},{"ts":"2026-04-23T09:37:34.286505+00:00","equity":39.4978},{"ts":"2026-04-23T09:38:40.322716+00:00","equity":39.4978},{"ts":"2026-04-23T09:39:38.933749+00:00","equity":39.4978},{"ts":"2026-04-23T09:40:45.323129+00:00","equity":39.4978},{"ts":"2026-04-23T09:41:34.161153+00:00","equity":39.4978},{"ts":"2026-04-23T09:42:39.179218+00:00","equity":39.4978},{"ts":"2026-04-23T09:43:42.052834+00:00","equity":39.4978},{"ts":"2026-04-23T09:44:35.270265+00:00","equity":39.4978},{"ts":"2026-04-23T09:45:43.233908+00:00","equity":39.4978},{"ts":"2026-04-23T09:46:37.740482+00:00","equity":39.4978},{"ts":"2026-04-23T09:47:42.371320+00:00","equity":39.4978},{"ts":"2026-04-23T09:48:38.485183+00:00","equity":39.4978},{"ts":"2026-04-23T09:49:38.239476+00:00","equity":39.4978},{"ts":"2026-04-23T09:50:44.869137+00:00","equity":39.4978},{"ts":"2026-04-23T09:51:35.969781+00:00","equity":39.4978},{"ts":"2026-04-23T09:52:30.696787+00:00","equity":39.4978},{"ts":"2026-04-23T09:53:36.037277+00:00","equity":39.4978},{"ts":"2026-04-23T09:54:33.241082+00:00","equity":39.4978},{"ts":"2026-04-23T09:55:42.437604+00:00","equity":39.4978},{"ts":"2026-04-23T09:56:34.617832+00:00","equity":39.4978},{"ts":"2026-04-23T09:57:36.691197+00:00","equity":39.4978},{"ts":"2026-04-23T09:58:34.598220+00:00","equity":39.4978},{"ts":"2026-04-23T09:59:36.660736+00:00","equity":39.4978},{"ts":"2026-04-23T10:01:06.576375+00:00","equity":39.4978},{"ts":"2026-04-23T10:02:40.280565+00:00","equity":39.4978},{"ts":"2026-04-23T10:03:39.538956+00:00","equity":39.4978},{"ts":"2026-04-23T10:04:33.519348+00:00","equity":39.4978},{"ts":"2026-04-23T10:05:36.336936+00:00","equity":39.4978},{"ts":"2026-04-23T10:06:39.537975+00:00","equity":39.4978},{"ts":"2026-04-23T10:07:38.744682+00:00","equity":39.4978},{"ts":"2026-04-23T10:08:37.715800+00:00","equity":39.4978},{"ts":"2026-04-23T10:09:37.061019+00:00","equity":39.4978},{"ts":"2026-04-23T10:10:45.541635+00:00","equity":39.4978},{"ts":"2026-04-23T10:11:38.879705+00:00","equity":39.4978},{"ts":"2026-04-23T10:12:38.569658+00:00","equity":39.4978},{"ts":"2026-04-23T10:13:39.594164+00:00","equity":39.4978},{"ts":"2026-04-23T10:14:41.935455+00:00","equity":39.4978},{"ts":"2026-04-23T10:15:43.659696+00:00","equity":39.4978},{"ts":"2026-04-23T10:16:40.842263+00:00","equity":39.4978},{"ts":"2026-04-23T10:17:36.850744+00:00","equity":39.4978},{"ts":"2026-04-23T10:18:36.479825+00:00","equity":39.4978},{"ts":"2026-04-23T10:19:33.415919+00:00","equity":39.4978},{"ts":"2026-04-23T10:20:43.628996+00:00","equity":39.4978},{"ts":"2026-04-23T10:21:38.752437+00:00","equity":39.4978},{"ts":"2026-04-23T10:22:37.137978+00:00","equity":39.4978},{"ts":"2026-04-23T10:23:35.095341+00:00","equity":39.4978},{"ts":"2026-04-23T10:24:39.191300+00:00","equity":39.4978},{"ts":"2026-04-23T10:25:37.983894+00:00","equity":39.4978},{"ts":"2026-04-23T10:26:37.565576+00:00","equity":39.4978},{"ts":"2026-04-23T10:27:33.700473+00:00","equity":39.4978},{"ts":"2026-04-23T10:28:39.371561+00:00","equity":39.4978},{"ts":"2026-04-23T10:29:35.516561+00:00","equity":39.4978},{"ts":"2026-04-23T10:30:55.755870+00:00","equity":39.4978},{"ts":"2026-04-23T10:31:33.414412+00:00","equity":39.4978},{"ts":"2026-04-23T10:32:37.582212+00:00","equity":39.4978},{"ts":"2026-04-23T10:33:34.737836+00:00","equity":39.4978},{"ts":"2026-04-23T10:34:36.013322+00:00","equity":39.4978},{"ts":"2026-04-23T10:35:41.261521+00:00","equity":39.4978},{"ts":"2026-04-23T10:36:39.116697+00:00","equity":39.4978},{"ts":"2026-04-23T10:37:37.121981+00:00","equity":39.4978},{"ts":"2026-04-23T10:38:43.050265+00:00","equity":39.4978},{"ts":"2026-04-23T10:39:34.858525+00:00","equity":39.4978},{"ts":"2026-04-23T10:40:42.269715+00:00","equity":39.4978},{"ts":"2026-04-23T10:41:39.262060+00:00","equity":39.4978},{"ts":"2026-04-23T10:42:39.213819+00:00","equity":39.4978},{"ts":"2026-04-23T10:43:36.636441+00:00","equity":39.4978},{"ts":"2026-04-23T10:44:38.378024+00:00","equity":39.4978},{"ts":"2026-04-23T10:45:43.202482+00:00","equity":39.4978},{"ts":"2026-04-23T10:46:46.101735+00:00","equity":39.4978},{"ts":"2026-04-23T10:47:21.529327+00:00","equity":39.4978},{"ts":"2026-04-23T10:48:42.198168+00:00","equity":39.4978},{"ts":"2026-04-23T10:49:32.518071+00:00","equity":39.4978},{"ts":"2026-04-23T10:50:43.291809+00:00","equity":39.4978},{"ts":"2026-04-23T10:51:33.516004+00:00","equity":39.4978},{"ts":"2026-04-23T10:52:41.202157+00:00","equity":39.4978},{"ts":"2026-04-23T10:53:37.355553+00:00","equity":39.4978},{"ts":"2026-04-23T10:54:37.213275+00:00","equity":39.4978},{"ts":"2026-04-23T10:55:43.376047+00:00","equity":39.4978},{"ts":"2026-04-23T10:56:34.392575+00:00","equity":39.4978},{"ts":"2026-04-23T10:57:35.348805+00:00","equity":39.4978},{"ts":"2026-04-23T10:58:38.920467+00:00","equity":39.4978},{"ts":"2026-04-23T10:59:38.254035+00:00","equity":39.4978},{"ts":"2026-04-23T11:01:10.597934+00:00","equity":39.4978},{"ts":"2026-04-23T11:02:38.462147+00:00","equity":39.4978},{"ts":"2026-04-23T11:03:35.619676+00:00","equity":39.4978},{"ts":"2026-04-23T11:04:36.704988+00:00","equity":39.4978},{"ts":"2026-04-23T11:05:41.735664+00:00","equity":39.4978},{"ts":"2026-04-23T11:06:41.951109+00:00","equity":39.4978},{"ts":"2026-04-23T11:07:37.422290+00:00","equity":39.4978},{"ts":"2026-04-23T11:08:35.763190+00:00","equity":39.4978},{"ts":"2026-04-23T11:09:39.022231+00:00","equity":39.4978},{"ts":"2026-04-23T11:10:46.772078+00:00","equity":39.4978},{"ts":"2026-04-23T11:11:37.414908+00:00","equity":39.4978},{"ts":"2026-04-23T11:12:38.381876+00:00","equity":39.4978},{"ts":"2026-04-23T11:13:36.036863+00:00","equity":39.4978},{"ts":"2026-04-23T11:14:37.477120+00:00","equity":39.4978},{"ts":"2026-04-23T11:15:43.874275+00:00","equity":39.4978},{"ts":"2026-04-23T11:16:36.950346+00:00","equity":39.4978},{"ts":"2026-04-23T11:17:39.530021+00:00","equity":39.4978},{"ts":"2026-04-23T11:18:35.937984+00:00","equity":39.4978},{"ts":"2026-04-23T11:19:36.442318+00:00","equity":39.4978},{"ts":"2026-04-23T11:20:43.120374+00:00","equity":39.4978},{"ts":"2026-04-23T11:21:37.353841+00:00","equity":39.4978},{"ts":"2026-04-23T11:22:36.754930+00:00","equity":39.4978},{"ts":"2026-04-23T11:23:35.132878+00:00","equity":39.4978},{"ts":"2026-04-23T11:24:39.865580+00:00","equity":39.4978},{"ts":"2026-04-23T11:25:36.082324+00:00","equity":39.4978},{"ts":"2026-04-23T11:26:36.772222+00:00","equity":39.4978},{"ts":"2026-04-23T11:27:35.733198+00:00","equity":39.4978},{"ts":"2026-04-23T11:28:38.300763+00:00","equity":39.4978},{"ts":"2026-04-23T11:29:33.647376+00:00","equity":39.4978},{"ts":"2026-04-23T11:31:00.289882+00:00","equity":39.4978},{"ts":"2026-04-23T11:31:37.044540+00:00","equity":39.4978},{"ts":"2026-04-23T11:32:37.605712+00:00","equity":39.4978},{"ts":"2026-04-23T11:33:34.329990+00:00","equity":39.4978},{"ts":"2026-04-23T11:34:38.100791+00:00","equity":39.4978},{"ts":"2026-04-23T11:35:38.647782+00:00","equity":39.4978},{"ts":"2026-04-23T11:36:36.580894+00:00","equity":39.4978},{"ts":"2026-04-23T11:37:39.872928+00:00","equity":39.4978},{"ts":"2026-04-23T11:38:39.914383+00:00","equity":39.4978},{"ts":"2026-04-23T11:39:36.883497+00:00","equity":39.4978},{"ts":"2026-04-23T11:40:44.202580+00:00","equity":39.4978}]},"account_b":{"name":"S4 (160\u20ac)","initial":160.0,"equity":158.6457,"cash":158.6457,"total_pnl":-0.9889,"total_pnl_pct":-0.85,"num_trades":23,"win_rate":39.1,"position":null,"trades":[{"side":"SHORT","entry_px":71014.59,"exit_px":70800.01,"exit_reason":"TIME_EXIT","pnl_net":0.0702,"pnl_pct":0.47,"leverage":2.32,"open_date":"2026-04-09T00:07:27.281013+00:00","close_date":"2026-04-09T00:37:29.797845+00:00"},{"side":"SHORT","entry_px":71310.14,"exit_px":72270.21,"exit_reason":"TIME_EXIT","pnl_net":-0.4697,"pnl_pct":-3.02,"leverage":2.09,"open_date":"2026-04-09T15:34:30.289889+00:00","close_date":"2026-04-09T16:04:38.081942+00:00"},{"side":"SHORT","entry_px":72238.7,"exit_px":71928.37,"exit_reason":"TIME_EXIT","pnl_net":0.1012,"pnl_pct":0.66,"leverage":2.0,"open_date":"2026-04-09T16:10:45.762962+00:00","close_date":"2026-04-09T16:40:35.619924+00:00"},{"side":"SHORT","entry_px":72132.38,"exit_px":72293.11,"exit_reason":"TIME_EXIT","pnl_net":-0.0984,"pnl_pct":-0.65,"leverage":2.0,"open_date":"2026-04-09T17:34:32.440549+00:00","close_date":"2026-04-09T18:04:29.684352+00:00"},{"side":"SHORT","entry_px":72178.16,"exit_px":71877.1,"exit_reason":"TIME_EXIT","pnl_net":0.0967,"pnl_pct":0.63,"leverage":2.0,"open_date":"2026-04-09T18:05:33.340863+00:00","close_date":"2026-04-09T18:35:34.470439+00:00"},{"side":"SHORT","entry_px":72198.57,"exit_px":72316.68,"exit_reason":"TIME_EXIT","pnl_net":-0.0804,"pnl_pct":-0.53,"leverage":2.0,"open_date":"2026-04-09T19:55:32.337855+00:00","close_date":"2026-04-09T20:25:29.183234+00:00"},{"side":"SHORT","entry_px":72236.1,"exit_px":72278.18,"exit_reason":"TIME_EXIT","pnl_net":-0.0481,"pnl_pct":-0.32,"leverage":2.0,"open_date":"2026-04-09T21:14:31.647826+00:00","close_date":"2026-04-09T21:44:32.950739+00:00"},{"side":"SHORT","entry_px":71815.44,"exit_px":71951.05,"exit_reason":"TIME_EXIT","pnl_net":-0.0922,"pnl_pct":-0.58,"leverage":2.02,"open_date":"2026-04-10T00:07:27.498788+00:00","close_date":"2026-04-10T00:37:28.193894+00:00"},{"side":"SHORT","entry_px":72227.07,"exit_px":72218.7,"exit_reason":"TIME_EXIT","pnl_net":-0.0276,"pnl_pct":-0.18,"leverage":2.0,"open_date":"2026-04-10T01:57:29.972133+00:00","close_date":"2026-04-10T02:27:25.773033+00:00"},{"side":"SHORT","entry_px":72235.52,"exit_px":72124.48,"exit_reason":"TIME_EXIT","pnl_net":0.0168,"pnl_pct":0.11,"leverage":2.0,"open_date":"2026-04-10T05:33:27.378197+00:00","close_date":"2026-04-10T06:03:27.036440+00:00"},{"side":"SHORT","entry_px":71648.45,"exit_px":71733.83,"exit_reason":"TIME_EXIT","pnl_net":-0.0708,"pnl_pct":-0.44,"leverage":2.0,"open_date":"2026-04-10T08:15:40.779037+00:00","close_date":"2026-04-10T08:45:38.484608+00:00"},{"side":"SHORT","entry_px":71699.73,"exit_px":71754.37,"exit_reason":"TIME_EXIT","pnl_net":-0.0569,"pnl_pct":-0.35,"leverage":2.0,"open_date":"2026-04-10T09:20:37.029983+00:00","close_date":"2026-04-10T09:50:34.257064+00:00"},{"side":"LONG","entry_px":72720.95,"exit_px":72801.09,"exit_reason":"TIME_EXIT","pnl_net":0.0038,"pnl_pct":0.02,"leverage":2.3,"open_date":"2026-04-11T06:31:26.079050+00:00","close_date":"2026-04-11T07:01:32.001496+00:00"},{"side":"LONG","entry_px":71750.2,"exit_px":71675.3,"exit_reason":"TIME_EXIT","pnl_net":-0.0664,"pnl_pct":-0.43,"leverage":2.11,"open_date":"2026-04-12T06:18:31.647507+00:00","close_date":"2026-04-12T06:48:33.656067+00:00"},{"side":"SHORT","entry_px":70817.98,"exit_px":70782.69,"exit_reason":"TIME_EXIT","pnl_net":-0.0153,"pnl_pct":-0.1,"leverage":2.0,"open_date":"2026-04-12T14:49:31.581232+00:00","close_date":"2026-04-12T15:19:31.557643+00:00"},{"side":"SHORT","entry_px":70782.69,"exit_px":70912.73,"exit_reason":"TIME_EXIT","pnl_net":-0.0865,"pnl_pct":-0.57,"leverage":2.0,"open_date":"2026-04-12T15:19:31.557733+00:00","close_date":"2026-04-12T15:49:29.823573+00:00"},{"side":"SHORT","entry_px":70805.59,"exit_px":70690.41,"exit_reason":"TIME_EXIT","pnl_net":0.0191,"pnl_pct":0.13,"leverage":2.0,"open_date":"2026-04-12T22:06:33.958590+00:00","close_date":"2026-04-12T22:36:29.596320+00:00"},{"side":"SHORT","entry_px":70820.73,"exit_px":70749.51,"exit_reason":"TIME_EXIT","pnl_net":0.0002,"pnl_pct":0.0,"leverage":2.0,"open_date":"2026-04-12T22:40:35.941504+00:00","close_date":"2026-04-12T23:10:43.110329+00:00"},{"side":"SHORT","entry_px":70681.25,"exit_px":71063.91,"exit_reason":"TIME_EXIT","pnl_net":-0.195,"pnl_pct":-1.28,"leverage":2.0,"open_date":"2026-04-13T00:08:28.139877+00:00","close_date":"2026-04-13T00:38:32.440183+00:00"},{"side":"SHORT","entry_px":70806.27,"exit_px":70713.49,"exit_reason":"TIME_EXIT","pnl_net":0.0095,"pnl_pct":0.06,"leverage":2.0,"open_date":"2026-04-13T05:13:30.616735+00:00","close_date":"2026-04-13T05:43:32.136462+00:00"},{"side":"SHORT","entry_px":70816.14,"exit_px":71010.73,"exit_reason":"TIME_EXIT","pnl_net":-0.114,"pnl_pct":-0.75,"leverage":2.0,"open_date":"2026-04-13T05:51:32.986920+00:00","close_date":"2026-04-13T06:21:28.800950+00:00"},{"side":"LONG","entry_px":72535.93,"exit_px":72156.26,"exit_reason":"TIME_EXIT","pnl_net":-0.2149,"pnl_pct":-1.37,"leverage":2.2,"open_date":"2026-04-13T17:34:38.784887+00:00","close_date":"2026-04-13T18:05:41.243283+00:00"},{"side":"LONG","entry_px":72510.19,"exit_px":73279.18,"exit_reason":"TIME_EXIT","pnl_net":0.3298,"pnl_pct":2.11,"leverage":2.2,"open_date":"2026-04-13T19:22:31.694978+00:00","close_date":"2026-04-13T19:52:33.690150+00:00"}],"equity_history":[{"ts":"2026-04-23T08:18:36.159978+00:00","equity":158.6457},{"ts":"2026-04-23T08:19:34.818420+00:00","equity":158.6457},{"ts":"2026-04-23T08:20:47.911289+00:00","equity":158.6457},{"ts":"2026-04-23T08:21:33.267871+00:00","equity":158.6457},{"ts":"2026-04-23T08:22:41.067605+00:00","equity":158.6457},{"ts":"2026-04-23T08:23:36.710453+00:00","equity":158.6457},{"ts":"2026-04-23T08:24:44.453592+00:00","equity":158.6457},{"ts":"2026-04-23T08:25:36.429366+00:00","equity":158.6457},{"ts":"2026-04-23T08:26:35.315153+00:00","equity":158.6457},{"ts":"2026-04-23T08:27:35.362341+00:00","equity":158.6457},{"ts":"2026-04-23T08:28:36.659188+00:00","equity":158.6457},{"ts":"2026-04-23T08:29:37.341238+00:00","equity":158.6457},{"ts":"2026-04-23T08:30:58.669753+00:00","equity":158.6457},{"ts":"2026-04-23T08:31:38.704137+00:00","equity":158.6457},{"ts":"2026-04-23T08:32:38.554726+00:00","equity":158.6457},{"ts":"2026-04-23T08:33:41.361243+00:00","equity":158.6457},{"ts":"2026-04-23T08:34:35.155669+00:00","equity":158.6457},{"ts":"2026-04-23T08:35:42.235951+00:00","equity":158.6457},{"ts":"2026-04-23T08:36:40.269010+00:00","equity":158.6457},{"ts":"2026-04-23T08:37:39.557022+00:00","equity":158.6457},{"ts":"2026-04-23T08:38:38.499686+00:00","equity":158.6457},{"ts":"2026-04-23T08:39:39.892584+00:00","equity":158.6457},{"ts":"2026-04-23T08:40:46.356706+00:00","equity":158.6457},{"ts":"2026-04-23T08:41:35.112642+00:00","equity":158.6457},{"ts":"2026-04-23T08:42:40.832905+00:00","equity":158.6457},{"ts":"2026-04-23T08:43:36.044517+00:00","equity":158.6457},{"ts":"2026-04-23T08:44:39.053143+00:00","equity":158.6457},{"ts":"2026-04-23T08:45:47.935929+00:00","equity":158.6457},{"ts":"2026-04-23T08:46:41.999638+00:00","equity":158.6457},{"ts":"2026-04-23T08:47:38.524483+00:00","equity":158.6457},{"ts":"2026-04-23T08:48:39.262762+00:00","equity":158.6457},{"ts":"2026-04-23T08:49:39.172408+00:00","equity":158.6457},{"ts":"2026-04-23T08:50:43.734640+00:00","equity":158.6457},{"ts":"2026-04-23T08:51:40.543173+00:00","equity":158.6457},{"ts":"2026-04-23T08:52:41.869840+00:00","equity":158.6457},{"ts":"2026-04-23T08:53:36.761513+00:00","equity":158.6457},{"ts":"2026-04-23T08:54:38.723617+00:00","equity":158.6457},{"ts":"2026-04-23T08:55:39.101737+00:00","equity":158.6457},{"ts":"2026-04-23T08:56:39.552569+00:00","equity":158.6457},{"ts":"2026-04-23T08:57:36.665023+00:00","equity":158.6457},{"ts":"2026-04-23T08:58:38.055669+00:00","equity":158.6457},{"ts":"2026-04-23T08:59:36.848813+00:00","equity":158.6457},{"ts":"2026-04-23T09:01:11.296319+00:00","equity":158.6457},{"ts":"2026-04-23T09:02:40.353331+00:00","equity":158.6457},{"ts":"2026-04-23T09:03:40.288922+00:00","equity":158.6457},{"ts":"2026-04-23T09:04:37.016920+00:00","equity":158.6457},{"ts":"2026-04-23T09:05:43.736501+00:00","equity":158.6457},{"ts":"2026-04-23T09:06:39.611812+00:00","equity":158.6457},{"ts":"2026-04-23T09:07:36.238192+00:00","equity":158.6457},{"ts":"2026-04-23T09:08:30.381128+00:00","equity":158.6457},{"ts":"2026-04-23T09:09:37.380995+00:00","equity":158.6457},{"ts":"2026-04-23T09:10:43.435460+00:00","equity":158.6457},{"ts":"2026-04-23T09:11:36.705062+00:00","equity":158.6457},{"ts":"2026-04-23T09:12:45.609337+00:00","equity":158.6457},{"ts":"2026-04-23T09:13:41.958643+00:00","equity":158.6457},{"ts":"2026-04-23T09:14:36.150340+00:00","equity":158.6457},{"ts":"2026-04-23T09:15:47.567943+00:00","equity":158.6457},{"ts":"2026-04-23T09:16:36.190671+00:00","equity":158.6457},{"ts":"2026-04-23T09:17:36.677987+00:00","equity":158.6457},{"ts":"2026-04-23T09:18:39.754378+00:00","equity":158.6457},{"ts":"2026-04-23T09:19:34.436099+00:00","equity":158.6457},{"ts":"2026-04-23T09:20:47.183282+00:00","equity":158.6457},{"ts":"2026-04-23T09:21:35.910242+00:00","equity":158.6457},{"ts":"2026-04-23T09:22:35.719039+00:00","equity":158.6457},{"ts":"2026-04-23T09:23:34.029383+00:00","equity":158.6457},{"ts":"2026-04-23T09:24:39.986824+00:00","equity":158.6457},{"ts":"2026-04-23T09:25:41.879233+00:00","equity":158.6457},{"ts":"2026-04-23T09:26:37.860486+00:00","equity":158.6457},{"ts":"2026-04-23T09:27:39.861939+00:00","equity":158.6457},{"ts":"2026-04-23T09:28:39.013505+00:00","equity":158.6457},{"ts":"2026-04-23T09:29:43.083387+00:00","equity":158.6457},{"ts":"2026-04-23T09:30:59.781577+00:00","equity":158.6457},{"ts":"2026-04-23T09:31:34.258965+00:00","equity":158.6457},{"ts":"2026-04-23T09:32:40.091842+00:00","equity":158.6457},{"ts":"2026-04-23T09:33:39.249508+00:00","equity":158.6457},{"ts":"2026-04-23T09:34:37.936396+00:00","equity":158.6457},{"ts":"2026-04-23T09:35:43.593981+00:00","equity":158.6457},{"ts":"2026-04-23T09:36:39.378736+00:00","equity":158.6457},{"ts":"2026-04-23T09:37:34.286530+00:00","equity":158.6457},{"ts":"2026-04-23T09:38:40.322741+00:00","equity":158.6457},{"ts":"2026-04-23T09:39:38.933773+00:00","equity":158.6457},{"ts":"2026-04-23T09:40:45.323157+00:00","equity":158.6457},{"ts":"2026-04-23T09:41:34.161177+00:00","equity":158.6457},{"ts":"2026-04-23T09:42:39.179242+00:00","equity":158.6457},{"ts":"2026-04-23T09:43:42.052860+00:00","equity":158.6457},{"ts":"2026-04-23T09:44:35.270285+00:00","equity":158.6457},{"ts":"2026-04-23T09:45:43.233930+00:00","equity":158.6457},{"ts":"2026-04-23T09:46:37.740507+00:00","equity":158.6457},{"ts":"2026-04-23T09:47:42.371365+00:00","equity":158.6457},{"ts":"2026-04-23T09:48:38.485207+00:00","equity":158.6457},{"ts":"2026-04-23T09:49:38.239500+00:00","equity":158.6457},{"ts":"2026-04-23T09:50:44.869163+00:00","equity":158.6457},{"ts":"2026-04-23T09:51:35.969809+00:00","equity":158.6457},{"ts":"2026-04-23T09:52:30.696811+00:00","equity":158.6457},{"ts":"2026-04-23T09:53:36.037302+00:00","equity":158.6457},{"ts":"2026-04-23T09:54:33.241109+00:00","equity":158.6457},{"ts":"2026-04-23T09:55:42.437628+00:00","equity":158.6457},{"ts":"2026-04-23T09:56:34.617859+00:00","equity":158.6457},{"ts":"2026-04-23T09:57:36.691226+00:00","equity":158.6457},{"ts":"2026-04-23T09:58:34.598246+00:00","equity":158.6457},{"ts":"2026-04-23T09:59:36.660762+00:00","equity":158.6457},{"ts":"2026-04-23T10:01:06.576415+00:00","equity":158.6457},{"ts":"2026-04-23T10:02:40.280590+00:00","equity":158.6457},{"ts":"2026-04-23T10:03:39.538980+00:00","equity":158.6457},{"ts":"2026-04-23T10:04:33.519374+00:00","equity":158.6457},{"ts":"2026-04-23T10:05:36.336964+00:00","equity":158.6457},{"ts":"2026-04-23T10:06:39.538003+00:00","equity":158.6457},{"ts":"2026-04-23T10:07:38.744706+00:00","equity":158.6457},{"ts":"2026-04-23T10:08:37.715825+00:00","equity":158.6457},{"ts":"2026-04-23T10:09:37.061045+00:00","equity":158.6457},{"ts":"2026-04-23T10:10:45.541659+00:00","equity":158.6457},{"ts":"2026-04-23T10:11:38.879734+00:00","equity":158.6457},{"ts":"2026-04-23T10:12:38.569681+00:00","equity":158.6457},{"ts":"2026-04-23T10:13:39.594191+00:00","equity":158.6457},{"ts":"2026-04-23T10:14:41.935480+00:00","equity":158.6457},{"ts":"2026-04-23T10:15:43.659719+00:00","equity":158.6457},{"ts":"2026-04-23T10:16:40.842288+00:00","equity":158.6457},{"ts":"2026-04-23T10:17:36.850768+00:00","equity":158.6457},{"ts":"2026-04-23T10:18:36.479849+00:00","equity":158.6457},{"ts":"2026-04-23T10:19:33.415943+00:00","equity":158.6457},{"ts":"2026-04-23T10:20:43.629021+00:00","equity":158.6457},{"ts":"2026-04-23T10:21:38.752465+00:00","equity":158.6457},{"ts":"2026-04-23T10:22:37.138003+00:00","equity":158.6457},{"ts":"2026-04-23T10:23:35.095368+00:00","equity":158.6457},{"ts":"2026-04-23T10:24:39.191323+00:00","equity":158.6457},{"ts":"2026-04-23T10:25:37.983919+00:00","equity":158.6457},{"ts":"2026-04-23T10:26:37.565603+00:00","equity":158.6457},{"ts":"2026-04-23T10:27:33.700495+00:00","equity":158.6457},{"ts":"2026-04-23T10:28:39.371582+00:00","equity":158.6457},{"ts":"2026-04-23T10:29:35.516586+00:00","equity":158.6457},{"ts":"2026-04-23T10:30:55.755897+00:00","equity":158.6457},{"ts":"2026-04-23T10:31:33.414436+00:00","equity":158.6457},{"ts":"2026-04-23T10:32:37.582240+00:00","equity":158.6457},{"ts":"2026-04-23T10:33:34.737870+00:00","equity":158.6457},{"ts":"2026-04-23T10:34:36.013343+00:00","equity":158.6457},{"ts":"2026-04-23T10:35:41.261544+00:00","equity":158.6457},{"ts":"2026-04-23T10:36:39.116721+00:00","equity":158.6457},{"ts":"2026-04-23T10:37:37.122005+00:00","equity":158.6457},{"ts":"2026-04-23T10:38:43.050288+00:00","equity":158.6457},{"ts":"2026-04-23T10:39:34.858550+00:00","equity":158.6457},{"ts":"2026-04-23T10:40:42.269739+00:00","equity":158.6457},{"ts":"2026-04-23T10:41:39.262083+00:00","equity":158.6457},{"ts":"2026-04-23T10:42:39.213842+00:00","equity":158.6457},{"ts":"2026-04-23T10:43:36.636467+00:00","equity":158.6457},{"ts":"2026-04-23T10:44:38.378048+00:00","equity":158.6457},{"ts":"2026-04-23T10:45:43.202503+00:00","equity":158.6457},{"ts":"2026-04-23T10:46:46.101761+00:00","equity":158.6457},{"ts":"2026-04-23T10:47:21.529353+00:00","equity":158.6457},{"ts":"2026-04-23T10:48:42.198191+00:00","equity":158.6457},{"ts":"2026-04-23T10:49:32.518098+00:00","equity":158.6457},{"ts":"2026-04-23T10:50:43.291832+00:00","equity":158.6457},{"ts":"2026-04-23T10:51:33.516030+00:00","equity":158.6457},{"ts":"2026-04-23T10:52:41.202182+00:00","equity":158.6457},{"ts":"2026-04-23T10:53:37.355578+00:00","equity":158.6457},{"ts":"2026-04-23T10:54:37.213300+00:00","equity":158.6457},{"ts":"2026-04-23T10:55:43.376071+00:00","equity":158.6457},{"ts":"2026-04-23T10:56:34.392605+00:00","equity":158.6457},{"ts":"2026-04-23T10:57:35.348829+00:00","equity":158.6457},{"ts":"2026-04-23T10:58:38.920489+00:00","equity":158.6457},{"ts":"2026-04-23T10:59:38.254060+00:00","equity":158.6457},{"ts":"2026-04-23T11:01:10.597961+00:00","equity":158.6457},{"ts":"2026-04-23T11:02:38.462172+00:00","equity":158.6457},{"ts":"2026-04-23T11:03:35.619701+00:00","equity":158.6457},{"ts":"2026-04-23T11:04:36.705016+00:00","equity":158.6457},{"ts":"2026-04-23T11:05:41.735686+00:00","equity":158.6457},{"ts":"2026-04-23T11:06:41.951132+00:00","equity":158.6457},{"ts":"2026-04-23T11:07:37.422320+00:00","equity":158.6457},{"ts":"2026-04-23T11:08:35.763216+00:00","equity":158.6457},{"ts":"2026-04-23T11:09:39.022255+00:00","equity":158.6457},{"ts":"2026-04-23T11:10:46.772104+00:00","equity":158.6457},{"ts":"2026-04-23T11:11:37.414931+00:00","equity":158.6457},{"ts":"2026-04-23T11:12:38.381901+00:00","equity":158.6457},{"ts":"2026-04-23T11:13:36.036887+00:00","equity":158.6457},{"ts":"2026-04-23T11:14:37.477143+00:00","equity":158.6457},{"ts":"2026-04-23T11:15:43.874298+00:00","equity":158.6457},{"ts":"2026-04-23T11:16:36.950374+00:00","equity":158.6457},{"ts":"2026-04-23T11:17:39.530052+00:00","equity":158.6457},{"ts":"2026-04-23T11:18:35.938034+00:00","equity":158.6457},{"ts":"2026-04-23T11:19:36.442341+00:00","equity":158.6457},{"ts":"2026-04-23T11:20:43.120402+00:00","equity":158.6457},{"ts":"2026-04-23T11:21:37.353864+00:00","equity":158.6457},{"ts":"2026-04-23T11:22:36.754954+00:00","equity":158.6457},{"ts":"2026-04-23T11:23:35.132903+00:00","equity":158.6457},{"ts":"2026-04-23T11:24:39.865605+00:00","equity":158.6457},{"ts":"2026-04-23T11:25:36.082351+00:00","equity":158.6457},{"ts":"2026-04-23T11:26:36.772247+00:00","equity":158.6457},{"ts":"2026-04-23T11:27:35.733223+00:00","equity":158.6457},{"ts":"2026-04-23T11:28:38.300787+00:00","equity":158.6457},{"ts":"2026-04-23T11:29:33.647402+00:00","equity":158.6457},{"ts":"2026-04-23T11:31:00.289906+00:00","equity":158.6457},{"ts":"2026-04-23T11:31:37.044565+00:00","equity":158.6457},{"ts":"2026-04-23T11:32:37.605740+00:00","equity":158.6457},{"ts":"2026-04-23T11:33:34.330015+00:00","equity":158.6457},{"ts":"2026-04-23T11:34:38.100816+00:00","equity":158.6457},{"ts":"2026-04-23T11:35:38.647810+00:00","equity":158.6457},{"ts":"2026-04-23T11:36:36.580918+00:00","equity":158.6457},{"ts":"2026-04-23T11:37:39.872953+00:00","equity":158.6457},{"ts":"2026-04-23T11:38:39.914407+00:00","equity":158.6457},{"ts":"2026-04-23T11:39:36.883522+00:00","equity":158.6457},{"ts":"2026-04-23T11:40:44.202604+00:00","equity":158.6457}]},"signal_history":[{"date":"2025-09-14","signal":"SHORT","price":115408.0},{"date":"2025-09-27","signal":"LONG","price":109682.0},{"date":"2025-10-18","signal":"LONG","price":107198.0},{"date":"2025-10-23","signal":"SHORT","price":110070.0},{"date":"2025-10-28","signal":"SHORT","price":112956.0},{"date":"2025-11-12","signal":"SHORT","price":101663.0},{"date":"2025-11-25","signal":"SHORT","price":87342.0},{"date":"2025-12-10","signal":"SHORT","price":92021.0},{"date":"2026-01-06","signal":"SHORT","price":93729.0},{"date":"2026-01-09","signal":"LONG","price":90513.0},{"date":"2026-02-02","signal":"SHORT","price":78689.0},{"date":"2026-02-09","signal":"SHORT","price":70121.0},{"date":"2026-02-16","signal":"SHORT","price":68843.0},{"date":"2026-02-22","signal":"SHORT","price":67659.0},{"date":"2026-03-11","signal":"SHORT","price":70205.0},{"date":"2026-03-20","signal":"LONG","price":70523.0},{"date":"2026-04-06","signal":"SHORT","price":68860.0},{"date":"2026-04-11","signal":"LONG","price":73054.0},{"date":"2026-04-12","signal":"SHORT","price":70753.0},{"date":"2026-04-13","signal":"LONG","price":74485.0}],"price_history":[{"date":"2026-01-24","close":89111.0},{"date":"2026-01-25","close":86572.0},{"date":"2026-01-26","close":88267.0},{"date":"2026-01-27","close":89103.0},{"date":"2026-01-28","close":89185.0},{"date":"2026-01-29","close":84562.0},{"date":"2026-01-30","close":84129.0},{"date":"2026-01-31","close":78621.0},{"date":"2026-02-01","close":76974.0},{"date":"2026-02-02","close":78689.0},{"date":"2026-02-03","close":75634.0},{"date":"2026-02-04","close":73020.0},{"date":"2026-02-05","close":62702.0},{"date":"2026-02-06","close":70555.0},{"date":"2026-02-07","close":69282.0},{"date":"2026-02-08","close":70265.0},{"date":"2026-02-09","close":70121.0},{"date":"2026-02-10","close":68794.0},{"date":"2026-02-11","close":66992.0},{"date":"2026-02-12","close":66222.0},{"date":"2026-02-13","close":68858.0},{"date":"2026-02-14","close":69768.0},{"date":"2026-02-15","close":68788.0},{"date":"2026-02-16","close":68843.0},{"date":"2026-02-17","close":67494.0},{"date":"2026-02-18","close":66425.0},{"date":"2026-02-19","close":66958.0},{"date":"2026-02-20","close":68005.0},{"date":"2026-02-21","close":68004.0},{"date":"2026-02-22","close":67659.0},{"date":"2026-02-23","close":64617.0},{"date":"2026-02-24","close":64080.0},{"date":"2026-02-25","close":67960.0},{"date":"2026-02-26","close":67454.0},{"date":"2026-02-27","close":65882.0},{"date":"2026-02-28","close":66996.0},{"date":"2026-03-01","close":65738.0},{"date":"2026-03-02","close":68776.0},{"date":"2026-03-03","close":68294.0},{"date":"2026-03-04","close":72711.0},{"date":"2026-03-05","close":70841.0},{"date":"2026-03-06","close":68136.0},{"date":"2026-03-07","close":67273.0},{"date":"2026-03-08","close":65970.0},{"date":"2026-03-09","close":68402.0},{"date":"2026-03-10","close":69927.0},{"date":"2026-03-11","close":70205.0},{"date":"2026-03-12","close":70493.0},{"date":"2026-03-13","close":70968.0},{"date":"2026-03-14","close":71215.0},{"date":"2026-03-15","close":72790.0},{"date":"2026-03-16","close":74861.0},{"date":"2026-03-17","close":73922.0},{"date":"2026-03-18","close":71246.0},{"date":"2026-03-19","close":69913.0},{"date":"2026-03-20","close":70523.0},{"date":"2026-03-21","close":68712.0},{"date":"2026-03-22","close":67845.0},{"date":"2026-03-23","close":70915.0},{"date":"2026-03-24","close":70518.0},{"date":"2026-03-25","close":71310.0},{"date":"2026-03-26","close":68792.0},{"date":"2026-03-27","close":66338.0},{"date":"2026-03-28","close":66320.0},{"date":"2026-03-29","close":65955.0},{"date":"2026-03-30","close":66691.0},{"date":"2026-03-31","close":68233.0},{"date":"2026-04-01","close":68079.0},{"date":"2026-04-02","close":66889.0},{"date":"2026-04-03","close":66931.0},{"date":"2026-04-04","close":67291.0},{"date":"2026-04-05","close":68982.0},{"date":"2026-04-06","close":68860.0},{"date":"2026-04-07","close":71941.0},{"date":"2026-04-08","close":71123.0},{"date":"2026-04-09","close":71768.0},{"date":"2026-04-10","close":72979.0},{"date":"2026-04-11","close":73054.0},{"date":"2026-04-12","close":70753.0},{"date":"2026-04-13","close":74485.0},{"date":"2026-04-14","close":74182.0},{"date":"2026-04-15","close":74805.0},{"date":"2026-04-16","close":75152.0},{"date":"2026-04-17","close":77127.0},{"date":"2026-04-18","close":75726.0},{"date":"2026-04-19","close":73856.0},{"date":"2026-04-20","close":75873.0},{"date":"2026-04-21","close":76353.0},{"date":"2026-04-22","close":78203.0},{"date":"2026-04-23","close":77535.0}],"portfolio_equity":198.1435,"portfolio_initial":200.0}