{"updated_at":"2026-04-18T10:15:41.150526+00:00","btc_price":76365.01,"btc_change_24h":-0.99,"current_signal":"neutral","last_signal_date":"2026-04-13","runs":13531,"account_a":{"name":"M1 (40\u20ac)","initial":40.0,"equity":39.4978,"cash":39.4978,"total_pnl":-0.3693,"total_pnl_pct":-1.26,"num_trades":23,"win_rate":39.1,"position":null,"trades":[{"side":"SHORT","entry_px":71014.59,"exit_px":70800.01,"exit_reason":"TIME_EXIT","pnl_net":0.0227,"pnl_pct":0.61,"leverage":3.0,"open_date":"2026-04-09T00:07:27.280958+00:00","close_date":"2026-04-09T00:37:29.797812+00:00"},{"side":"SHORT","entry_px":71310.14,"exit_px":72270.21,"exit_reason":"TIME_EXIT","pnl_net":-0.1689,"pnl_pct":-4.34,"leverage":3.0,"open_date":"2026-04-09T15:34:30.289830+00:00","close_date":"2026-04-09T16:04:38.081910+00:00"},{"side":"SHORT","entry_px":72238.7,"exit_px":71928.37,"exit_reason":"TIME_EXIT","pnl_net":0.0379,"pnl_pct":0.99,"leverage":3.0,"open_date":"2026-04-09T16:10:45.762905+00:00","close_date":"2026-04-09T16:40:35.619888+00:00"},{"side":"SHORT","entry_px":72132.38,"exit_px":72293.11,"exit_reason":"TIME_EXIT","pnl_net":-0.0369,"pnl_pct":-0.97,"leverage":3.0,"open_date":"2026-04-09T17:34:32.440495+00:00","close_date":"2026-04-09T18:04:29.684322+00:00"},{"side":"SHORT","entry_px":72178.16,"exit_px":71877.1,"exit_reason":"TIME_EXIT","pnl_net":0.0362,"pnl_pct":0.95,"leverage":3.0,"open_date":"2026-04-09T18:05:33.340811+00:00","close_date":"2026-04-09T18:35:34.470407+00:00"},{"side":"SHORT","entry_px":72198.57,"exit_px":72316.68,"exit_reason":"TIME_EXIT","pnl_net":-0.0301,"pnl_pct":-0.79,"leverage":3.0,"open_date":"2026-04-09T19:55:32.337788+00:00","close_date":"2026-04-09T20:25:29.183202+00:00"},{"side":"SHORT","entry_px":72236.1,"exit_px":72278.18,"exit_reason":"TIME_EXIT","pnl_net":-0.018,"pnl_pct":-0.47,"leverage":3.0,"open_date":"2026-04-09T21:14:31.647775+00:00","close_date":"2026-04-09T21:44:32.950707+00:00"},{"side":"SHORT","entry_px":71815.44,"exit_px":71951.05,"exit_reason":"TIME_EXIT","pnl_net":-0.0342,"pnl_pct":-0.87,"leverage":3.0,"open_date":"2026-04-10T00:07:27.498736+00:00","close_date":"2026-04-10T00:37:28.193865+00:00"},{"side":"SHORT","entry_px":72227.07,"exit_px":72218.7,"exit_reason":"TIME_EXIT","pnl_net":-0.0103,"pnl_pct":-0.27,"leverage":3.0,"open_date":"2026-04-10T01:57:29.972077+00:00","close_date":"2026-04-10T02:27:25.772993+00:00"},{"side":"SHORT","entry_px":72235.52,"exit_px":72124.48,"exit_reason":"TIME_EXIT","pnl_net":0.0063,"pnl_pct":0.16,"leverage":3.0,"open_date":"2026-04-10T05:33:27.378141+00:00","close_date":"2026-04-10T06:03:27.036407+00:00"},{"side":"SHORT","entry_px":71648.45,"exit_px":71733.83,"exit_reason":"TIME_EXIT","pnl_net":-0.0265,"pnl_pct":-0.66,"leverage":3.0,"open_date":"2026-04-10T08:15:40.778984+00:00","close_date":"2026-04-10T08:45:38.484577+00:00"},{"side":"SHORT","entry_px":71699.73,"exit_px":71754.37,"exit_reason":"TIME_EXIT","pnl_net":-0.0213,"pnl_pct":-0.53,"leverage":3.0,"open_date":"2026-04-10T09:20:37.029930+00:00","close_date":"2026-04-10T09:50:34.257031+00:00"},{"side":"LONG","entry_px":72720.95,"exit_px":72801.09,"exit_reason":"TIME_EXIT","pnl_net":0.0012,"pnl_pct":0.03,"leverage":3.0,"open_date":"2026-04-11T06:31:26.078999+00:00","close_date":"2026-04-11T07:01:32.001463+00:00"},{"side":"LONG","entry_px":71750.2,"exit_px":71675.3,"exit_reason":"TIME_EXIT","pnl_net":-0.0235,"pnl_pct":-0.61,"leverage":3.0,"open_date":"2026-04-12T06:18:31.647450+00:00","close_date":"2026-04-12T06:48:33.656037+00:00"},{"side":"SHORT","entry_px":70817.98,"exit_px":70782.69,"exit_reason":"TIME_EXIT","pnl_net":-0.0057,"pnl_pct":-0.15,"leverage":3.0,"open_date":"2026-04-12T14:49:31.581180+00:00","close_date":"2026-04-12T15:19:31.557594+00:00"},{"side":"SHORT","entry_px":70782.69,"exit_px":70912.73,"exit_reason":"TIME_EXIT","pnl_net":-0.0324,"pnl_pct":-0.85,"leverage":3.0,"open_date":"2026-04-12T15:19:31.557694+00:00","close_date":"2026-04-12T15:49:29.823540+00:00"},{"side":"SHORT","entry_px":70805.59,"exit_px":70690.41,"exit_reason":"TIME_EXIT","pnl_net":0.0071,"pnl_pct":0.19,"leverage":3.0,"open_date":"2026-04-12T22:06:33.958533+00:00","close_date":"2026-04-12T22:36:29.596287+00:00"},{"side":"SHORT","entry_px":70820.73,"exit_px":70749.51,"exit_reason":"TIME_EXIT","pnl_net":0.0001,"pnl_pct":0.0,"leverage":3.0,"open_date":"2026-04-12T22:40:35.941449+00:00","close_date":"2026-04-12T23:10:43.110297+00:00"},{"side":"SHORT","entry_px":70681.25,"exit_px":71063.91,"exit_reason":"TIME_EXIT","pnl_net":-0.0729,"pnl_pct":-1.92,"leverage":3.0,"open_date":"2026-04-13T00:08:28.139824+00:00","close_date":"2026-04-13T00:38:32.440151+00:00"},{"side":"SHORT","entry_px":70806.27,"exit_px":70713.49,"exit_reason":"TIME_EXIT","pnl_net":0.0035,"pnl_pct":0.09,"leverage":3.0,"open_date":"2026-04-13T05:13:30.616682+00:00","close_date":"2026-04-13T05:43:32.136431+00:00"},{"side":"SHORT","entry_px":70816.14,"exit_px":71010.73,"exit_reason":"TIME_EXIT","pnl_net":-0.0426,"pnl_pct":-1.12,"leverage":3.0,"open_date":"2026-04-13T05:51:32.986866+00:00","close_date":"2026-04-13T06:21:28.800920+00:00"},{"side":"LONG","entry_px":72535.93,"exit_px":72156.26,"exit_reason":"TIME_EXIT","pnl_net":-0.0729,"pnl_pct":-1.87,"leverage":3.0,"open_date":"2026-04-13T17:34:38.784833+00:00","close_date":"2026-04-13T18:05:41.243229+00:00"},{"side":"LONG","entry_px":72510.19,"exit_px":73279.18,"exit_reason":"TIME_EXIT","pnl_net":0.1119,"pnl_pct":2.88,"leverage":3.0,"open_date":"2026-04-13T19:22:31.694920+00:00","close_date":"2026-04-13T19:52:33.690112+00:00"}],"equity_history":[{"ts":"2026-04-18T06:54:33.019429+00:00","equity":39.4978},{"ts":"2026-04-18T06:55:35.492815+00:00","equity":39.4978},{"ts":"2026-04-18T06:56:37.690924+00:00","equity":39.4978},{"ts":"2026-04-18T06:57:33.758844+00:00","equity":39.4978},{"ts":"2026-04-18T06:58:30.578160+00:00","equity":39.4978},{"ts":"2026-04-18T06:59:34.228456+00:00","equity":39.4978},{"ts":"2026-04-18T07:01:04.642479+00:00","equity":39.4978},{"ts":"2026-04-18T07:02:34.563529+00:00","equity":39.4978},{"ts":"2026-04-18T07:03:35.068824+00:00","equity":39.4978},{"ts":"2026-04-18T07:04:36.168558+00:00","equity":39.4978},{"ts":"2026-04-18T07:05:37.131801+00:00","equity":39.4978},{"ts":"2026-04-18T07:06:35.130409+00:00","equity":39.4978},{"ts":"2026-04-18T07:07:30.653661+00:00","equity":39.4978},{"ts":"2026-04-18T07:08:32.444688+00:00","equity":39.4978},{"ts":"2026-04-18T07:09:32.365840+00:00","equity":39.4978},{"ts":"2026-04-18T07:10:39.485070+00:00","equity":39.4978},{"ts":"2026-04-18T07:11:30.267336+00:00","equity":39.4978},{"ts":"2026-04-18T07:12:30.417313+00:00","equity":39.4978},{"ts":"2026-04-18T07:13:34.039453+00:00","equity":39.4978},{"ts":"2026-04-18T07:14:31.681667+00:00","equity":39.4978},{"ts":"2026-04-18T07:15:39.857739+00:00","equity":39.4978},{"ts":"2026-04-18T07:16:32.621420+00:00","equity":39.4978},{"ts":"2026-04-18T07:17:30.460899+00:00","equity":39.4978},{"ts":"2026-04-18T07:18:40.198352+00:00","equity":39.4978},{"ts":"2026-04-18T07:19:34.441645+00:00","equity":39.4978},{"ts":"2026-04-18T07:20:37.591666+00:00","equity":39.4978},{"ts":"2026-04-18T07:21:31.309612+00:00","equity":39.4978},{"ts":"2026-04-18T07:22:34.180604+00:00","equity":39.4978},{"ts":"2026-04-18T07:23:34.253167+00:00","equity":39.4978},{"ts":"2026-04-18T07:24:30.246454+00:00","equity":39.4978},{"ts":"2026-04-18T07:25:33.415606+00:00","equity":39.4978},{"ts":"2026-04-18T07:26:33.925858+00:00","equity":39.4978},{"ts":"2026-04-18T07:27:29.864855+00:00","equity":39.4978},{"ts":"2026-04-18T07:28:33.890497+00:00","equity":39.4978},{"ts":"2026-04-18T07:29:32.189329+00:00","equity":39.4978},{"ts":"2026-04-18T07:30:53.426337+00:00","equity":39.4978},{"ts":"2026-04-18T07:31:33.222740+00:00","equity":39.4978},{"ts":"2026-04-18T07:32:35.537872+00:00","equity":39.4978},{"ts":"2026-04-18T07:33:29.252337+00:00","equity":39.4978},{"ts":"2026-04-18T07:34:34.135427+00:00","equity":39.4978},{"ts":"2026-04-18T07:35:34.323739+00:00","equity":39.4978},{"ts":"2026-04-18T07:36:31.375168+00:00","equity":39.4978},{"ts":"2026-04-18T07:37:34.936952+00:00","equity":39.4978},{"ts":"2026-04-18T07:38:30.534751+00:00","equity":39.4978},{"ts":"2026-04-18T07:39:37.199265+00:00","equity":39.4978},{"ts":"2026-04-18T07:40:38.853703+00:00","equity":39.4978},{"ts":"2026-04-18T07:41:31.427621+00:00","equity":39.4978},{"ts":"2026-04-18T07:42:37.295942+00:00","equity":39.4978},{"ts":"2026-04-18T07:43:26.592403+00:00","equity":39.4978},{"ts":"2026-04-18T07:44:34.814006+00:00","equity":39.4978},{"ts":"2026-04-18T07:45:38.312537+00:00","equity":39.4978},{"ts":"2026-04-18T07:46:30.769521+00:00","equity":39.4978},{"ts":"2026-04-18T07:47:32.267654+00:00","equity":39.4978},{"ts":"2026-04-18T07:48:33.975544+00:00","equity":39.4978},{"ts":"2026-04-18T07:49:06.941105+00:00","equity":39.4978},{"ts":"2026-04-18T07:50:40.407789+00:00","equity":39.4978},{"ts":"2026-04-18T07:51:34.775837+00:00","equity":39.4978},{"ts":"2026-04-18T07:52:31.149954+00:00","equity":39.4978},{"ts":"2026-04-18T07:53:30.129022+00:00","equity":39.4978},{"ts":"2026-04-18T07:54:32.082484+00:00","equity":39.4978},{"ts":"2026-04-18T07:55:38.325750+00:00","equity":39.4978},{"ts":"2026-04-18T07:56:33.073662+00:00","equity":39.4978},{"ts":"2026-04-18T07:57:30.520828+00:00","equity":39.4978},{"ts":"2026-04-18T07:58:36.587039+00:00","equity":39.4978},{"ts":"2026-04-18T07:59:25.837837+00:00","equity":39.4978},{"ts":"2026-04-18T08:01:04.103635+00:00","equity":39.4978},{"ts":"2026-04-18T08:02:30.089993+00:00","equity":39.4978},{"ts":"2026-04-18T08:03:30.395051+00:00","equity":39.4978},{"ts":"2026-04-18T08:04:30.058210+00:00","equity":39.4978},{"ts":"2026-04-18T08:05:35.709822+00:00","equity":39.4978},{"ts":"2026-04-18T08:06:33.967014+00:00","equity":39.4978},{"ts":"2026-04-18T08:07:32.967607+00:00","equity":39.4978},{"ts":"2026-04-18T08:08:31.020045+00:00","equity":39.4978},{"ts":"2026-04-18T08:09:30.890042+00:00","equity":39.4978},{"ts":"2026-04-18T08:10:37.086618+00:00","equity":39.4978},{"ts":"2026-04-18T08:11:31.156131+00:00","equity":39.4978},{"ts":"2026-04-18T08:12:32.603357+00:00","equity":39.4978},{"ts":"2026-04-18T08:13:30.747483+00:00","equity":39.4978},{"ts":"2026-04-18T08:14:36.400204+00:00","equity":39.4978},{"ts":"2026-04-18T08:15:41.407335+00:00","equity":39.4978},{"ts":"2026-04-18T08:16:33.293092+00:00","equity":39.4978},{"ts":"2026-04-18T08:17:31.686451+00:00","equity":39.4978},{"ts":"2026-04-18T08:18:34.164413+00:00","equity":39.4978},{"ts":"2026-04-18T08:19:30.344240+00:00","equity":39.4978},{"ts":"2026-04-18T08:20:37.533307+00:00","equity":39.4978},{"ts":"2026-04-18T08:21:34.025803+00:00","equity":39.4978},{"ts":"2026-04-18T08:22:32.905268+00:00","equity":39.4978},{"ts":"2026-04-18T08:23:31.856109+00:00","equity":39.4978},{"ts":"2026-04-18T08:24:33.792760+00:00","equity":39.4978},{"ts":"2026-04-18T08:25:33.196795+00:00","equity":39.4978},{"ts":"2026-04-18T08:26:35.188376+00:00","equity":39.4978},{"ts":"2026-04-18T08:27:34.750890+00:00","equity":39.4978},{"ts":"2026-04-18T08:28:32.704327+00:00","equity":39.4978},{"ts":"2026-04-18T08:29:31.722053+00:00","equity":39.4978},{"ts":"2026-04-18T08:30:51.577734+00:00","equity":39.4978},{"ts":"2026-04-18T08:31:33.698427+00:00","equity":39.4978},{"ts":"2026-04-18T08:32:35.880043+00:00","equity":39.4978},{"ts":"2026-04-18T08:33:30.437592+00:00","equity":39.4978},{"ts":"2026-04-18T08:34:36.086679+00:00","equity":39.4978},{"ts":"2026-04-18T08:35:35.073108+00:00","equity":39.4978},{"ts":"2026-04-18T08:36:35.566887+00:00","equity":39.4978},{"ts":"2026-04-18T08:37:29.002626+00:00","equity":39.4978},{"ts":"2026-04-18T08:38:34.051085+00:00","equity":39.4978},{"ts":"2026-04-18T08:39:31.952291+00:00","equity":39.4978},{"ts":"2026-04-18T08:40:36.345415+00:00","equity":39.4978},{"ts":"2026-04-18T08:41:30.602830+00:00","equity":39.4978},{"ts":"2026-04-18T08:42:36.364441+00:00","equity":39.4978},{"ts":"2026-04-18T08:43:34.679169+00:00","equity":39.4978},{"ts":"2026-04-18T08:44:36.449872+00:00","equity":39.4978},{"ts":"2026-04-18T08:45:38.919746+00:00","equity":39.4978},{"ts":"2026-04-18T08:46:35.619873+00:00","equity":39.4978},{"ts":"2026-04-18T08:47:28.020262+00:00","equity":39.4978},{"ts":"2026-04-18T08:48:33.166838+00:00","equity":39.4978},{"ts":"2026-04-18T08:49:30.529483+00:00","equity":39.4978},{"ts":"2026-04-18T08:50:37.105211+00:00","equity":39.4978},{"ts":"2026-04-18T08:51:30.147052+00:00","equity":39.4978},{"ts":"2026-04-18T08:52:36.639734+00:00","equity":39.4978},{"ts":"2026-04-18T08:53:33.266571+00:00","equity":39.4978},{"ts":"2026-04-18T08:54:31.024542+00:00","equity":39.4978},{"ts":"2026-04-18T08:55:35.824042+00:00","equity":39.4978},{"ts":"2026-04-18T08:56:33.136104+00:00","equity":39.4978},{"ts":"2026-04-18T08:57:32.781332+00:00","equity":39.4978},{"ts":"2026-04-18T08:58:33.051702+00:00","equity":39.4978},{"ts":"2026-04-18T08:59:31.516068+00:00","equity":39.4978},{"ts":"2026-04-18T09:01:01.383753+00:00","equity":39.4978},{"ts":"2026-04-18T09:01:34.383386+00:00","equity":39.4978},{"ts":"2026-04-18T09:02:30.243654+00:00","equity":39.4978},{"ts":"2026-04-18T09:03:45.579905+00:00","equity":39.4978},{"ts":"2026-04-18T09:04:30.743728+00:00","equity":39.4978},{"ts":"2026-04-18T09:05:33.050008+00:00","equity":39.4978},{"ts":"2026-04-18T09:06:31.415292+00:00","equity":39.4978},{"ts":"2026-04-18T09:07:29.823169+00:00","equity":39.4978},{"ts":"2026-04-18T09:08:35.374770+00:00","equity":39.4978},{"ts":"2026-04-18T09:09:29.466206+00:00","equity":39.4978},{"ts":"2026-04-18T09:10:40.305417+00:00","equity":39.4978},{"ts":"2026-04-18T09:11:27.973279+00:00","equity":39.4978},{"ts":"2026-04-18T09:12:35.358114+00:00","equity":39.4978},{"ts":"2026-04-18T09:13:33.677837+00:00","equity":39.4978},{"ts":"2026-04-18T09:14:39.272097+00:00","equity":39.4978},{"ts":"2026-04-18T09:15:40.290541+00:00","equity":39.4978},{"ts":"2026-04-18T09:16:35.574119+00:00","equity":39.4978},{"ts":"2026-04-18T09:17:34.185924+00:00","equity":39.4978},{"ts":"2026-04-18T09:18:36.982760+00:00","equity":39.4978},{"ts":"2026-04-18T09:19:34.085747+00:00","equity":39.4978},{"ts":"2026-04-18T09:20:37.309188+00:00","equity":39.4978},{"ts":"2026-04-18T09:21:30.943156+00:00","equity":39.4978},{"ts":"2026-04-18T09:22:36.461674+00:00","equity":39.4978},{"ts":"2026-04-18T09:23:30.554538+00:00","equity":39.4978},{"ts":"2026-04-18T09:24:35.682926+00:00","equity":39.4978},{"ts":"2026-04-18T09:25:35.538314+00:00","equity":39.4978},{"ts":"2026-04-18T09:26:36.997587+00:00","equity":39.4978},{"ts":"2026-04-18T09:27:34.220177+00:00","equity":39.4978},{"ts":"2026-04-18T09:28:32.199547+00:00","equity":39.4978},{"ts":"2026-04-18T09:29:34.316408+00:00","equity":39.4978},{"ts":"2026-04-18T09:30:50.905021+00:00","equity":39.4978},{"ts":"2026-04-18T09:31:32.550133+00:00","equity":39.4978},{"ts":"2026-04-18T09:32:33.135832+00:00","equity":39.4978},{"ts":"2026-04-18T09:33:29.608265+00:00","equity":39.4978},{"ts":"2026-04-18T09:34:35.151456+00:00","equity":39.4978},{"ts":"2026-04-18T09:35:33.829298+00:00","equity":39.4978},{"ts":"2026-04-18T09:36:34.117953+00:00","equity":39.4978},{"ts":"2026-04-18T09:37:32.984056+00:00","equity":39.4978},{"ts":"2026-04-18T09:38:30.697216+00:00","equity":39.4978},{"ts":"2026-04-18T09:39:35.941349+00:00","equity":39.4978},{"ts":"2026-04-18T09:40:40.518282+00:00","equity":39.4978},{"ts":"2026-04-18T09:41:36.138083+00:00","equity":39.4978},{"ts":"2026-04-18T09:42:35.510259+00:00","equity":39.4978},{"ts":"2026-04-18T09:43:29.874880+00:00","equity":39.4978},{"ts":"2026-04-18T09:44:33.666824+00:00","equity":39.4978},{"ts":"2026-04-18T09:45:41.458022+00:00","equity":39.4978},{"ts":"2026-04-18T09:46:31.341326+00:00","equity":39.4978},{"ts":"2026-04-18T09:47:30.688698+00:00","equity":39.4978},{"ts":"2026-04-18T09:48:34.353262+00:00","equity":39.4978},{"ts":"2026-04-18T09:49:29.173740+00:00","equity":39.4978},{"ts":"2026-04-18T09:50:35.232216+00:00","equity":39.4978},{"ts":"2026-04-18T09:51:35.003531+00:00","equity":39.4978},{"ts":"2026-04-18T09:52:36.418320+00:00","equity":39.4978},{"ts":"2026-04-18T09:53:35.448643+00:00","equity":39.4978},{"ts":"2026-04-18T09:54:35.248095+00:00","equity":39.4978},{"ts":"2026-04-18T09:55:32.104444+00:00","equity":39.4978},{"ts":"2026-04-18T09:56:34.350411+00:00","equity":39.4978},{"ts":"2026-04-18T09:57:33.132284+00:00","equity":39.4978},{"ts":"2026-04-18T09:58:36.113882+00:00","equity":39.4978},{"ts":"2026-04-18T09:59:30.415726+00:00","equity":39.4978},{"ts":"2026-04-18T10:01:00.638202+00:00","equity":39.4978},{"ts":"2026-04-18T10:01:33.215768+00:00","equity":39.4978},{"ts":"2026-04-18T10:02:33.620410+00:00","equity":39.4978},{"ts":"2026-04-18T10:03:31.684368+00:00","equity":39.4978},{"ts":"2026-04-18T10:04:31.682786+00:00","equity":39.4978},{"ts":"2026-04-18T10:05:37.127749+00:00","equity":39.4978},{"ts":"2026-04-18T10:06:31.801428+00:00","equity":39.4978},{"ts":"2026-04-18T10:07:32.190203+00:00","equity":39.4978},{"ts":"2026-04-18T10:08:32.195058+00:00","equity":39.4978},{"ts":"2026-04-18T10:09:35.493172+00:00","equity":39.4978},{"ts":"2026-04-18T10:10:41.382494+00:00","equity":39.4978},{"ts":"2026-04-18T10:11:28.018443+00:00","equity":39.4978},{"ts":"2026-04-18T10:12:31.773929+00:00","equity":39.4978},{"ts":"2026-04-18T10:13:33.008098+00:00","equity":39.4978},{"ts":"2026-04-18T10:14:34.209497+00:00","equity":39.4978},{"ts":"2026-04-18T10:15:41.135506+00:00","equity":39.4978}]},"account_b":{"name":"S4 (160\u20ac)","initial":160.0,"equity":158.6457,"cash":158.6457,"total_pnl":-0.9889,"total_pnl_pct":-0.85,"num_trades":23,"win_rate":39.1,"position":null,"trades":[{"side":"SHORT","entry_px":71014.59,"exit_px":70800.01,"exit_reason":"TIME_EXIT","pnl_net":0.0702,"pnl_pct":0.47,"leverage":2.32,"open_date":"2026-04-09T00:07:27.281013+00:00","close_date":"2026-04-09T00:37:29.797845+00:00"},{"side":"SHORT","entry_px":71310.14,"exit_px":72270.21,"exit_reason":"TIME_EXIT","pnl_net":-0.4697,"pnl_pct":-3.02,"leverage":2.09,"open_date":"2026-04-09T15:34:30.289889+00:00","close_date":"2026-04-09T16:04:38.081942+00:00"},{"side":"SHORT","entry_px":72238.7,"exit_px":71928.37,"exit_reason":"TIME_EXIT","pnl_net":0.1012,"pnl_pct":0.66,"leverage":2.0,"open_date":"2026-04-09T16:10:45.762962+00:00","close_date":"2026-04-09T16:40:35.619924+00:00"},{"side":"SHORT","entry_px":72132.38,"exit_px":72293.11,"exit_reason":"TIME_EXIT","pnl_net":-0.0984,"pnl_pct":-0.65,"leverage":2.0,"open_date":"2026-04-09T17:34:32.440549+00:00","close_date":"2026-04-09T18:04:29.684352+00:00"},{"side":"SHORT","entry_px":72178.16,"exit_px":71877.1,"exit_reason":"TIME_EXIT","pnl_net":0.0967,"pnl_pct":0.63,"leverage":2.0,"open_date":"2026-04-09T18:05:33.340863+00:00","close_date":"2026-04-09T18:35:34.470439+00:00"},{"side":"SHORT","entry_px":72198.57,"exit_px":72316.68,"exit_reason":"TIME_EXIT","pnl_net":-0.0804,"pnl_pct":-0.53,"leverage":2.0,"open_date":"2026-04-09T19:55:32.337855+00:00","close_date":"2026-04-09T20:25:29.183234+00:00"},{"side":"SHORT","entry_px":72236.1,"exit_px":72278.18,"exit_reason":"TIME_EXIT","pnl_net":-0.0481,"pnl_pct":-0.32,"leverage":2.0,"open_date":"2026-04-09T21:14:31.647826+00:00","close_date":"2026-04-09T21:44:32.950739+00:00"},{"side":"SHORT","entry_px":71815.44,"exit_px":71951.05,"exit_reason":"TIME_EXIT","pnl_net":-0.0922,"pnl_pct":-0.58,"leverage":2.02,"open_date":"2026-04-10T00:07:27.498788+00:00","close_date":"2026-04-10T00:37:28.193894+00:00"},{"side":"SHORT","entry_px":72227.07,"exit_px":72218.7,"exit_reason":"TIME_EXIT","pnl_net":-0.0276,"pnl_pct":-0.18,"leverage":2.0,"open_date":"2026-04-10T01:57:29.972133+00:00","close_date":"2026-04-10T02:27:25.773033+00:00"},{"side":"SHORT","entry_px":72235.52,"exit_px":72124.48,"exit_reason":"TIME_EXIT","pnl_net":0.0168,"pnl_pct":0.11,"leverage":2.0,"open_date":"2026-04-10T05:33:27.378197+00:00","close_date":"2026-04-10T06:03:27.036440+00:00"},{"side":"SHORT","entry_px":71648.45,"exit_px":71733.83,"exit_reason":"TIME_EXIT","pnl_net":-0.0708,"pnl_pct":-0.44,"leverage":2.0,"open_date":"2026-04-10T08:15:40.779037+00:00","close_date":"2026-04-10T08:45:38.484608+00:00"},{"side":"SHORT","entry_px":71699.73,"exit_px":71754.37,"exit_reason":"TIME_EXIT","pnl_net":-0.0569,"pnl_pct":-0.35,"leverage":2.0,"open_date":"2026-04-10T09:20:37.029983+00:00","close_date":"2026-04-10T09:50:34.257064+00:00"},{"side":"LONG","entry_px":72720.95,"exit_px":72801.09,"exit_reason":"TIME_EXIT","pnl_net":0.0038,"pnl_pct":0.02,"leverage":2.3,"open_date":"2026-04-11T06:31:26.079050+00:00","close_date":"2026-04-11T07:01:32.001496+00:00"},{"side":"LONG","entry_px":71750.2,"exit_px":71675.3,"exit_reason":"TIME_EXIT","pnl_net":-0.0664,"pnl_pct":-0.43,"leverage":2.11,"open_date":"2026-04-12T06:18:31.647507+00:00","close_date":"2026-04-12T06:48:33.656067+00:00"},{"side":"SHORT","entry_px":70817.98,"exit_px":70782.69,"exit_reason":"TIME_EXIT","pnl_net":-0.0153,"pnl_pct":-0.1,"leverage":2.0,"open_date":"2026-04-12T14:49:31.581232+00:00","close_date":"2026-04-12T15:19:31.557643+00:00"},{"side":"SHORT","entry_px":70782.69,"exit_px":70912.73,"exit_reason":"TIME_EXIT","pnl_net":-0.0865,"pnl_pct":-0.57,"leverage":2.0,"open_date":"2026-04-12T15:19:31.557733+00:00","close_date":"2026-04-12T15:49:29.823573+00:00"},{"side":"SHORT","entry_px":70805.59,"exit_px":70690.41,"exit_reason":"TIME_EXIT","pnl_net":0.0191,"pnl_pct":0.13,"leverage":2.0,"open_date":"2026-04-12T22:06:33.958590+00:00","close_date":"2026-04-12T22:36:29.596320+00:00"},{"side":"SHORT","entry_px":70820.73,"exit_px":70749.51,"exit_reason":"TIME_EXIT","pnl_net":0.0002,"pnl_pct":0.0,"leverage":2.0,"open_date":"2026-04-12T22:40:35.941504+00:00","close_date":"2026-04-12T23:10:43.110329+00:00"},{"side":"SHORT","entry_px":70681.25,"exit_px":71063.91,"exit_reason":"TIME_EXIT","pnl_net":-0.195,"pnl_pct":-1.28,"leverage":2.0,"open_date":"2026-04-13T00:08:28.139877+00:00","close_date":"2026-04-13T00:38:32.440183+00:00"},{"side":"SHORT","entry_px":70806.27,"exit_px":70713.49,"exit_reason":"TIME_EXIT","pnl_net":0.0095,"pnl_pct":0.06,"leverage":2.0,"open_date":"2026-04-13T05:13:30.616735+00:00","close_date":"2026-04-13T05:43:32.136462+00:00"},{"side":"SHORT","entry_px":70816.14,"exit_px":71010.73,"exit_reason":"TIME_EXIT","pnl_net":-0.114,"pnl_pct":-0.75,"leverage":2.0,"open_date":"2026-04-13T05:51:32.986920+00:00","close_date":"2026-04-13T06:21:28.800950+00:00"},{"side":"LONG","entry_px":72535.93,"exit_px":72156.26,"exit_reason":"TIME_EXIT","pnl_net":-0.2149,"pnl_pct":-1.37,"leverage":2.2,"open_date":"2026-04-13T17:34:38.784887+00:00","close_date":"2026-04-13T18:05:41.243283+00:00"},{"side":"LONG","entry_px":72510.19,"exit_px":73279.18,"exit_reason":"TIME_EXIT","pnl_net":0.3298,"pnl_pct":2.11,"leverage":2.2,"open_date":"2026-04-13T19:22:31.694978+00:00","close_date":"2026-04-13T19:52:33.690150+00:00"}],"equity_history":[{"ts":"2026-04-18T06:54:33.019455+00:00","equity":158.6457},{"ts":"2026-04-18T06:55:35.492839+00:00","equity":158.6457},{"ts":"2026-04-18T06:56:37.690948+00:00","equity":158.6457},{"ts":"2026-04-18T06:57:33.758867+00:00","equity":158.6457},{"ts":"2026-04-18T06:58:30.578185+00:00","equity":158.6457},{"ts":"2026-04-18T06:59:34.228486+00:00","equity":158.6457},{"ts":"2026-04-18T07:01:04.642504+00:00","equity":158.6457},{"ts":"2026-04-18T07:02:34.563559+00:00","equity":158.6457},{"ts":"2026-04-18T07:03:35.068849+00:00","equity":158.6457},{"ts":"2026-04-18T07:04:36.168584+00:00","equity":158.6457},{"ts":"2026-04-18T07:05:37.131824+00:00","equity":158.6457},{"ts":"2026-04-18T07:06:35.130434+00:00","equity":158.6457},{"ts":"2026-04-18T07:07:30.653687+00:00","equity":158.6457},{"ts":"2026-04-18T07:08:32.444712+00:00","equity":158.6457},{"ts":"2026-04-18T07:09:32.365862+00:00","equity":158.6457},{"ts":"2026-04-18T07:10:39.485095+00:00","equity":158.6457},{"ts":"2026-04-18T07:11:30.267361+00:00","equity":158.6457},{"ts":"2026-04-18T07:12:30.417339+00:00","equity":158.6457},{"ts":"2026-04-18T07:13:34.039479+00:00","equity":158.6457},{"ts":"2026-04-18T07:14:31.681692+00:00","equity":158.6457},{"ts":"2026-04-18T07:15:39.857764+00:00","equity":158.6457},{"ts":"2026-04-18T07:16:32.621446+00:00","equity":158.6457},{"ts":"2026-04-18T07:17:30.460924+00:00","equity":158.6457},{"ts":"2026-04-18T07:18:40.198376+00:00","equity":158.6457},{"ts":"2026-04-18T07:19:34.441672+00:00","equity":158.6457},{"ts":"2026-04-18T07:20:37.591693+00:00","equity":158.6457},{"ts":"2026-04-18T07:21:31.309640+00:00","equity":158.6457},{"ts":"2026-04-18T07:22:34.180629+00:00","equity":158.6457},{"ts":"2026-04-18T07:23:34.253191+00:00","equity":158.6457},{"ts":"2026-04-18T07:24:30.246480+00:00","equity":158.6457},{"ts":"2026-04-18T07:25:33.415631+00:00","equity":158.6457},{"ts":"2026-04-18T07:26:33.925884+00:00","equity":158.6457},{"ts":"2026-04-18T07:27:29.864879+00:00","equity":158.6457},{"ts":"2026-04-18T07:28:33.890523+00:00","equity":158.6457},{"ts":"2026-04-18T07:29:32.189353+00:00","equity":158.6457},{"ts":"2026-04-18T07:30:53.426362+00:00","equity":158.6457},{"ts":"2026-04-18T07:31:33.222764+00:00","equity":158.6457},{"ts":"2026-04-18T07:32:35.537901+00:00","equity":158.6457},{"ts":"2026-04-18T07:33:29.252362+00:00","equity":158.6457},{"ts":"2026-04-18T07:34:34.135448+00:00","equity":158.6457},{"ts":"2026-04-18T07:35:34.323762+00:00","equity":158.6457},{"ts":"2026-04-18T07:36:31.375195+00:00","equity":158.6457},{"ts":"2026-04-18T07:37:34.936976+00:00","equity":158.6457},{"ts":"2026-04-18T07:38:30.534775+00:00","equity":158.6457},{"ts":"2026-04-18T07:39:37.199292+00:00","equity":158.6457},{"ts":"2026-04-18T07:40:38.853726+00:00","equity":158.6457},{"ts":"2026-04-18T07:41:31.427650+00:00","equity":158.6457},{"ts":"2026-04-18T07:42:37.295968+00:00","equity":158.6457},{"ts":"2026-04-18T07:43:26.592441+00:00","equity":158.6457},{"ts":"2026-04-18T07:44:34.814031+00:00","equity":158.6457},{"ts":"2026-04-18T07:45:38.312566+00:00","equity":158.6457},{"ts":"2026-04-18T07:46:30.769547+00:00","equity":158.6457},{"ts":"2026-04-18T07:47:32.267678+00:00","equity":158.6457},{"ts":"2026-04-18T07:48:33.975568+00:00","equity":158.6457},{"ts":"2026-04-18T07:49:06.941128+00:00","equity":158.6457},{"ts":"2026-04-18T07:50:40.407815+00:00","equity":158.6457},{"ts":"2026-04-18T07:51:34.775862+00:00","equity":158.6457},{"ts":"2026-04-18T07:52:31.149979+00:00","equity":158.6457},{"ts":"2026-04-18T07:53:30.129050+00:00","equity":158.6457},{"ts":"2026-04-18T07:54:32.082510+00:00","equity":158.6457},{"ts":"2026-04-18T07:55:38.325779+00:00","equity":158.6457},{"ts":"2026-04-18T07:56:33.073689+00:00","equity":158.6457},{"ts":"2026-04-18T07:57:30.520855+00:00","equity":158.6457},{"ts":"2026-04-18T07:58:36.587096+00:00","equity":158.6457},{"ts":"2026-04-18T07:59:25.837861+00:00","equity":158.6457},{"ts":"2026-04-18T08:01:04.103661+00:00","equity":158.6457},{"ts":"2026-04-18T08:02:30.090019+00:00","equity":158.6457},{"ts":"2026-04-18T08:03:30.395075+00:00","equity":158.6457},{"ts":"2026-04-18T08:04:30.058237+00:00","equity":158.6457},{"ts":"2026-04-18T08:05:35.709847+00:00","equity":158.6457},{"ts":"2026-04-18T08:06:33.967041+00:00","equity":158.6457},{"ts":"2026-04-18T08:07:32.967631+00:00","equity":158.6457},{"ts":"2026-04-18T08:08:31.020069+00:00","equity":158.6457},{"ts":"2026-04-18T08:09:30.890070+00:00","equity":158.6457},{"ts":"2026-04-18T08:10:37.086643+00:00","equity":158.6457},{"ts":"2026-04-18T08:11:31.156158+00:00","equity":158.6457},{"ts":"2026-04-18T08:12:32.603383+00:00","equity":158.6457},{"ts":"2026-04-18T08:13:30.747508+00:00","equity":158.6457},{"ts":"2026-04-18T08:14:36.400233+00:00","equity":158.6457},{"ts":"2026-04-18T08:15:41.407359+00:00","equity":158.6457},{"ts":"2026-04-18T08:16:33.293120+00:00","equity":158.6457},{"ts":"2026-04-18T08:17:31.686477+00:00","equity":158.6457},{"ts":"2026-04-18T08:18:34.164437+00:00","equity":158.6457},{"ts":"2026-04-18T08:19:30.344268+00:00","equity":158.6457},{"ts":"2026-04-18T08:20:37.533330+00:00","equity":158.6457},{"ts":"2026-04-18T08:21:34.025828+00:00","equity":158.6457},{"ts":"2026-04-18T08:22:32.905293+00:00","equity":158.6457},{"ts":"2026-04-18T08:23:31.856133+00:00","equity":158.6457},{"ts":"2026-04-18T08:24:33.792807+00:00","equity":158.6457},{"ts":"2026-04-18T08:25:33.196821+00:00","equity":158.6457},{"ts":"2026-04-18T08:26:35.188398+00:00","equity":158.6457},{"ts":"2026-04-18T08:27:34.750913+00:00","equity":158.6457},{"ts":"2026-04-18T08:28:32.704354+00:00","equity":158.6457},{"ts":"2026-04-18T08:29:31.722076+00:00","equity":158.6457},{"ts":"2026-04-18T08:30:51.577757+00:00","equity":158.6457},{"ts":"2026-04-18T08:31:33.698454+00:00","equity":158.6457},{"ts":"2026-04-18T08:32:35.880079+00:00","equity":158.6457},{"ts":"2026-04-18T08:33:30.437616+00:00","equity":158.6457},{"ts":"2026-04-18T08:34:36.086705+00:00","equity":158.6457},{"ts":"2026-04-18T08:35:35.073134+00:00","equity":158.6457},{"ts":"2026-04-18T08:36:35.566914+00:00","equity":158.6457},{"ts":"2026-04-18T08:37:29.002651+00:00","equity":158.6457},{"ts":"2026-04-18T08:38:34.051114+00:00","equity":158.6457},{"ts":"2026-04-18T08:39:31.952316+00:00","equity":158.6457},{"ts":"2026-04-18T08:40:36.345438+00:00","equity":158.6457},{"ts":"2026-04-18T08:41:30.602855+00:00","equity":158.6457},{"ts":"2026-04-18T08:42:36.364501+00:00","equity":158.6457},{"ts":"2026-04-18T08:43:34.679193+00:00","equity":158.6457},{"ts":"2026-04-18T08:44:36.449895+00:00","equity":158.6457},{"ts":"2026-04-18T08:45:38.919774+00:00","equity":158.6457},{"ts":"2026-04-18T08:46:35.619902+00:00","equity":158.6457},{"ts":"2026-04-18T08:47:28.020290+00:00","equity":158.6457},{"ts":"2026-04-18T08:48:33.166862+00:00","equity":158.6457},{"ts":"2026-04-18T08:49:30.529511+00:00","equity":158.6457},{"ts":"2026-04-18T08:50:37.105239+00:00","equity":158.6457},{"ts":"2026-04-18T08:51:30.147078+00:00","equity":158.6457},{"ts":"2026-04-18T08:52:36.639758+00:00","equity":158.6457},{"ts":"2026-04-18T08:53:33.266595+00:00","equity":158.6457},{"ts":"2026-04-18T08:54:31.024567+00:00","equity":158.6457},{"ts":"2026-04-18T08:55:35.824065+00:00","equity":158.6457},{"ts":"2026-04-18T08:56:33.136130+00:00","equity":158.6457},{"ts":"2026-04-18T08:57:32.781360+00:00","equity":158.6457},{"ts":"2026-04-18T08:58:33.051725+00:00","equity":158.6457},{"ts":"2026-04-18T08:59:31.516112+00:00","equity":158.6457},{"ts":"2026-04-18T09:01:01.383779+00:00","equity":158.6457},{"ts":"2026-04-18T09:01:34.383410+00:00","equity":158.6457},{"ts":"2026-04-18T09:02:30.243681+00:00","equity":158.6457},{"ts":"2026-04-18T09:03:45.579929+00:00","equity":158.6457},{"ts":"2026-04-18T09:04:30.743756+00:00","equity":158.6457},{"ts":"2026-04-18T09:05:33.050034+00:00","equity":158.6457},{"ts":"2026-04-18T09:06:31.415316+00:00","equity":158.6457},{"ts":"2026-04-18T09:07:29.823193+00:00","equity":158.6457},{"ts":"2026-04-18T09:08:35.374795+00:00","equity":158.6457},{"ts":"2026-04-18T09:09:29.466229+00:00","equity":158.6457},{"ts":"2026-04-18T09:10:40.305442+00:00","equity":158.6457},{"ts":"2026-04-18T09:11:27.973307+00:00","equity":158.6457},{"ts":"2026-04-18T09:12:35.358138+00:00","equity":158.6457},{"ts":"2026-04-18T09:13:33.677862+00:00","equity":158.6457},{"ts":"2026-04-18T09:14:39.272122+00:00","equity":158.6457},{"ts":"2026-04-18T09:15:40.290568+00:00","equity":158.6457},{"ts":"2026-04-18T09:16:35.574145+00:00","equity":158.6457},{"ts":"2026-04-18T09:17:34.185947+00:00","equity":158.6457},{"ts":"2026-04-18T09:18:36.982782+00:00","equity":158.6457},{"ts":"2026-04-18T09:19:34.085773+00:00","equity":158.6457},{"ts":"2026-04-18T09:20:37.309212+00:00","equity":158.6457},{"ts":"2026-04-18T09:21:30.943181+00:00","equity":158.6457},{"ts":"2026-04-18T09:22:36.461696+00:00","equity":158.6457},{"ts":"2026-04-18T09:23:30.554564+00:00","equity":158.6457},{"ts":"2026-04-18T09:24:35.682952+00:00","equity":158.6457},{"ts":"2026-04-18T09:25:35.538338+00:00","equity":158.6457},{"ts":"2026-04-18T09:26:36.997614+00:00","equity":158.6457},{"ts":"2026-04-18T09:27:34.220205+00:00","equity":158.6457},{"ts":"2026-04-18T09:28:32.199573+00:00","equity":158.6457},{"ts":"2026-04-18T09:29:34.316437+00:00","equity":158.6457},{"ts":"2026-04-18T09:30:50.905046+00:00","equity":158.6457},{"ts":"2026-04-18T09:31:32.550159+00:00","equity":158.6457},{"ts":"2026-04-18T09:32:33.135856+00:00","equity":158.6457},{"ts":"2026-04-18T09:33:29.608291+00:00","equity":158.6457},{"ts":"2026-04-18T09:34:35.151481+00:00","equity":158.6457},{"ts":"2026-04-18T09:35:33.829324+00:00","equity":158.6457},{"ts":"2026-04-18T09:36:34.117977+00:00","equity":158.6457},{"ts":"2026-04-18T09:37:32.984080+00:00","equity":158.6457},{"ts":"2026-04-18T09:38:30.697242+00:00","equity":158.6457},{"ts":"2026-04-18T09:39:35.941376+00:00","equity":158.6457},{"ts":"2026-04-18T09:40:40.518306+00:00","equity":158.6457},{"ts":"2026-04-18T09:41:36.138109+00:00","equity":158.6457},{"ts":"2026-04-18T09:42:35.510284+00:00","equity":158.6457},{"ts":"2026-04-18T09:43:29.874905+00:00","equity":158.6457},{"ts":"2026-04-18T09:44:33.666850+00:00","equity":158.6457},{"ts":"2026-04-18T09:45:41.458047+00:00","equity":158.6457},{"ts":"2026-04-18T09:46:31.341350+00:00","equity":158.6457},{"ts":"2026-04-18T09:47:30.688723+00:00","equity":158.6457},{"ts":"2026-04-18T09:48:34.353286+00:00","equity":158.6457},{"ts":"2026-04-18T09:49:29.173768+00:00","equity":158.6457},{"ts":"2026-04-18T09:50:35.232243+00:00","equity":158.6457},{"ts":"2026-04-18T09:51:35.003553+00:00","equity":158.6457},{"ts":"2026-04-18T09:52:36.418344+00:00","equity":158.6457},{"ts":"2026-04-18T09:53:35.448668+00:00","equity":158.6457},{"ts":"2026-04-18T09:54:35.248120+00:00","equity":158.6457},{"ts":"2026-04-18T09:55:32.104469+00:00","equity":158.6457},{"ts":"2026-04-18T09:56:34.350435+00:00","equity":158.6457},{"ts":"2026-04-18T09:57:33.132306+00:00","equity":158.6457},{"ts":"2026-04-18T09:58:36.113906+00:00","equity":158.6457},{"ts":"2026-04-18T09:59:30.415754+00:00","equity":158.6457},{"ts":"2026-04-18T10:01:00.638226+00:00","equity":158.6457},{"ts":"2026-04-18T10:01:33.215793+00:00","equity":158.6457},{"ts":"2026-04-18T10:02:33.620435+00:00","equity":158.6457},{"ts":"2026-04-18T10:03:31.684394+00:00","equity":158.6457},{"ts":"2026-04-18T10:04:31.682812+00:00","equity":158.6457},{"ts":"2026-04-18T10:05:37.127775+00:00","equity":158.6457},{"ts":"2026-04-18T10:06:31.801454+00:00","equity":158.6457},{"ts":"2026-04-18T10:07:32.190227+00:00","equity":158.6457},{"ts":"2026-04-18T10:08:32.195083+00:00","equity":158.6457},{"ts":"2026-04-18T10:09:35.493195+00:00","equity":158.6457},{"ts":"2026-04-18T10:10:41.382520+00:00","equity":158.6457},{"ts":"2026-04-18T10:11:28.018470+00:00","equity":158.6457},{"ts":"2026-04-18T10:12:31.773952+00:00","equity":158.6457},{"ts":"2026-04-18T10:13:33.008124+00:00","equity":158.6457},{"ts":"2026-04-18T10:14:34.209524+00:00","equity":158.6457},{"ts":"2026-04-18T10:15:41.135531+00:00","equity":158.6457}]},"signal_history":[{"date":"2025-09-14","signal":"SHORT","price":115408.0},{"date":"2025-09-27","signal":"LONG","price":109682.0},{"date":"2025-10-18","signal":"LONG","price":107198.0},{"date":"2025-10-23","signal":"SHORT","price":110070.0},{"date":"2025-10-28","signal":"SHORT","price":112956.0},{"date":"2025-11-12","signal":"SHORT","price":101663.0},{"date":"2025-11-25","signal":"SHORT","price":87342.0},{"date":"2025-12-10","signal":"SHORT","price":92021.0},{"date":"2026-01-06","signal":"SHORT","price":93729.0},{"date":"2026-01-09","signal":"LONG","price":90513.0},{"date":"2026-02-02","signal":"SHORT","price":78689.0},{"date":"2026-02-09","signal":"SHORT","price":70121.0},{"date":"2026-02-16","signal":"SHORT","price":68843.0},{"date":"2026-02-22","signal":"SHORT","price":67659.0},{"date":"2026-03-11","signal":"SHORT","price":70205.0},{"date":"2026-03-20","signal":"LONG","price":70523.0},{"date":"2026-04-06","signal":"SHORT","price":68860.0},{"date":"2026-04-11","signal":"LONG","price":73054.0},{"date":"2026-04-12","signal":"SHORT","price":70753.0},{"date":"2026-04-13","signal":"LONG","price":74485.0}],"price_history":[{"date":"2026-01-19","close":92554.0},{"date":"2026-01-20","close":88311.0},{"date":"2026-01-21","close":89377.0},{"date":"2026-01-22","close":89462.0},{"date":"2026-01-23","close":89504.0},{"date":"2026-01-24","close":89111.0},{"date":"2026-01-25","close":86572.0},{"date":"2026-01-26","close":88267.0},{"date":"2026-01-27","close":89103.0},{"date":"2026-01-28","close":89185.0},{"date":"2026-01-29","close":84562.0},{"date":"2026-01-30","close":84129.0},{"date":"2026-01-31","close":78621.0},{"date":"2026-02-01","close":76974.0},{"date":"2026-02-02","close":78689.0},{"date":"2026-02-03","close":75634.0},{"date":"2026-02-04","close":73020.0},{"date":"2026-02-05","close":62702.0},{"date":"2026-02-06","close":70555.0},{"date":"2026-02-07","close":69282.0},{"date":"2026-02-08","close":70265.0},{"date":"2026-02-09","close":70121.0},{"date":"2026-02-10","close":68794.0},{"date":"2026-02-11","close":66992.0},{"date":"2026-02-12","close":66222.0},{"date":"2026-02-13","close":68858.0},{"date":"2026-02-14","close":69768.0},{"date":"2026-02-15","close":68788.0},{"date":"2026-02-16","close":68843.0},{"date":"2026-02-17","close":67494.0},{"date":"2026-02-18","close":66425.0},{"date":"2026-02-19","close":66958.0},{"date":"2026-02-20","close":68005.0},{"date":"2026-02-21","close":68004.0},{"date":"2026-02-22","close":67659.0},{"date":"2026-02-23","close":64617.0},{"date":"2026-02-24","close":64080.0},{"date":"2026-02-25","close":67960.0},{"date":"2026-02-26","close":67454.0},{"date":"2026-02-27","close":65882.0},{"date":"2026-02-28","close":66996.0},{"date":"2026-03-01","close":65738.0},{"date":"2026-03-02","close":68776.0},{"date":"2026-03-03","close":68294.0},{"date":"2026-03-04","close":72711.0},{"date":"2026-03-05","close":70841.0},{"date":"2026-03-06","close":68136.0},{"date":"2026-03-07","close":67273.0},{"date":"2026-03-08","close":65970.0},{"date":"2026-03-09","close":68402.0},{"date":"2026-03-10","close":69927.0},{"date":"2026-03-11","close":70205.0},{"date":"2026-03-12","close":70493.0},{"date":"2026-03-13","close":70968.0},{"date":"2026-03-14","close":71215.0},{"date":"2026-03-15","close":72790.0},{"date":"2026-03-16","close":74861.0},{"date":"2026-03-17","close":73922.0},{"date":"2026-03-18","close":71246.0},{"date":"2026-03-19","close":69913.0},{"date":"2026-03-20","close":70523.0},{"date":"2026-03-21","close":68712.0},{"date":"2026-03-22","close":67845.0},{"date":"2026-03-23","close":70915.0},{"date":"2026-03-24","close":70518.0},{"date":"2026-03-25","close":71310.0},{"date":"2026-03-26","close":68792.0},{"date":"2026-03-27","close":66338.0},{"date":"2026-03-28","close":66320.0},{"date":"2026-03-29","close":65955.0},{"date":"2026-03-30","close":66691.0},{"date":"2026-03-31","close":68233.0},{"date":"2026-04-01","close":68079.0},{"date":"2026-04-02","close":66889.0},{"date":"2026-04-03","close":66931.0},{"date":"2026-04-04","close":67291.0},{"date":"2026-04-05","close":68982.0},{"date":"2026-04-06","close":68860.0},{"date":"2026-04-07","close":71941.0},{"date":"2026-04-08","close":71123.0},{"date":"2026-04-09","close":71768.0},{"date":"2026-04-10","close":72979.0},{"date":"2026-04-11","close":73054.0},{"date":"2026-04-12","close":70753.0},{"date":"2026-04-13","close":74485.0},{"date":"2026-04-14","close":74182.0},{"date":"2026-04-15","close":74805.0},{"date":"2026-04-16","close":75152.0},{"date":"2026-04-17","close":77127.0},{"date":"2026-04-18","close":76365.0}],"portfolio_equity":198.1435,"portfolio_initial":200.0}